[
  {
    "id": 6293417,
    "slug": "live-eredivisie-go-ahead-treft-utrecht-en-kan-ajax-weer-inhalen-op-ranglijst",
    "type": "article",
    "title": "Live Eredivisie | Go Ahead treft Utrecht en kan Ajax weer inhalen op ranglijst",
    "subtitle": null,
    "published_at": "2023-12-10T11:58:32+01:00",
    "updated_at": "2023-12-10T11:58:33+01:00",
    "media_id": "rzoxkaiaf6ie",
    "duration": null,
    "canonical_section": {
      "id": 1772338,
      "slug": "voetbal",
      "type": "default",
      "name": "Voetbal",
      "style": "nusport",
      "media_id": null,
      "partner": null
    },
    "url": "/voetbal/6293417/live-eredivisie-go-ahead-treft-utrecht-en-kan-ajax-weer-inhalen-op-ranglijst.html",
    "open_new_window": false,
    "partner": null
  },
  {
    "id": 6292905,
    "slug": "belasting-op-frisdrank-straks-drie-keer-zo-hoog-ook-op-havermelk",
    "type": "article",
    "title": "Belasting op 'frisdrank' straks drie keer zo hoog, óók op havermelk",
    "subtitle": null,
    "published_at": "2023-12-10T11:57:10+01:00",
    "updated_at": "2023-12-10T11:59:50+01:00",
    "media_id": "1e8xab4avzjr",
    "duration": null,
    "canonical_section": {
      "id": 99,
      "slug": "economie",
      "type": "default",
      "name": "Economie",
      "style": "nuzakelijk",
      "media_id": null,
      "partner": null
    },
    "url": "/economie/6292905/belasting-op-frisdrank-straks-drie-keer-zo-hoog-ook-op-havermelk.html",
    "open_new_window": false,
    "partner": null
  },
  {
    "id": 6293420,
    "slug": "23-jarige-man-dood-gevonden-in-woning-oss-twee-vrouwen-aangehouden",
    "type": "article",
    "title": "23-jarige man dood gevonden in woning Oss, twee vrouwen aangehouden",
    "subtitle": null,
    "published_at": "2023-12-10T11:49:40+01:00",
    "updated_at": "2023-12-10T12:01:10+01:00",
    "media_id": "jgxxc7qat4yg",
    "duration": null,
    "canonical_section": {
      "id": 1771435,
      "slug": "binnenland",
      "type": "default",
      "name": "Binnenland",
      "style": "nu",
      "media_id": null,
      "partner": null
    },
    "url": "/binnenland/6293420/23-jarige-man-dood-gevonden-in-woning-oss-twee-vrouwen-aangehouden.html",
    "open_new_window": false,
    "partner": null
  },
  {
    "id": 6293170,
    "slug": "digitaal-gekochte-serie-mag-je-niet-altijd-houden-koopknop-is-misleidend",
    "type": "article",
    "title": "Digitaal gekochte serie mag je niet altijd houden: 'Koopknop is misleidend'",
    "subtitle": "NU+",
    "published_at": "2023-12-10T11:26:35+01:00",
    "updated_at": "2023-12-10T11:52:55+01:00",
    "media_id": "q6vx5spalskp",
    "duration": null,
    "canonical_section": {
      "id": 1771438,
      "slug": "tech",
      "type": "default",
      "name": "Tech",
      "style": "nutech",
      "media_id": null,
      "partner": null
    },
    "url": "/tech/6293170/digitaal-gekochte-serie-mag-je-niet-altijd-houden-koopknop-is-misleidend.html",
    "open_new_window": false,
    "partner": null
  },
  {
    "id": 6293414,
    "slug": "martin-bosma-pvv-doet-nieuwe-poging-om-kamervoorzitter-te-worden",
    "type": "article",
    "title": "Martin Bosma (PVV) doet nieuwe poging om Kamervoorzitter te worden",
    "subtitle": null,
    "published_at": "2023-12-10T11:03:43+01:00",
    "updated_at": "2023-12-10T11:38:07+01:00",
    "media_id": "gugxrtuauize",
    "duration": null,
    "canonical_section": {
      "id": 1771437,
      "slug": "politiek",
      "type": "default",
      "name": "Politiek",
      "style": "nu",
      "media_id": null,
      "partner": null
    },
    "url": "/politiek/6293414/martin-bosma-pvv-doet-nieuwe-poging-om-kamervoorzitter-te-worden.html",
    "open_new_window": false,
    "partner": null
  },
  {
    "id": 6293344,
    "slug": "als-de-frisdrankbelasting-straks-is-verdrievoudigd-koop-ik-dat-minder",
    "type": "article",
    "title": "'Als de frisdrankbelasting straks is verdrievoudigd, koop ik dat minder'",
    "subtitle": "Stelling",
    "published_at": "2023-12-10T11:01:58+01:00",
    "updated_at": "2023-12-10T11:02:00+01:00",
    "media_id": "ixzxczdawo6z",
    "duration": null,
    "canonical_section": {
      "id": 1779134,
      "slug": "stelling",
      "type": "default",
      "name": "Stelling en Praat Mee",
      "style": "nu",
      "media_id": null,
      "partner": null
    },
    "url": "/stelling/6293344/als-de-frisdrankbelasting-straks-is-verdrievoudigd-koop-ik-dat-minder.html",
    "open_new_window": false,
    "partner": null
  },
  {
    "id": 6293412,
    "slug": "klimaatactivisten-kleuren-kanaal-in-venetie-gifgroen",
    "type": "video",
    "title": "Klimaatactivisten kleuren kanaal in Venetië gifgroen",
    "subtitle": "Video",
    "published_at": "2023-12-10T10:56:54+01:00",
    "updated_at": "2023-12-10T10:57:06+01:00",
    "media_id": "w1pxhtgamc53",
    "duration": "0:35",
    "canonical_section": {
      "id": 1772431,
      "slug": "videos",
      "type": "default",
      "name": "Video's",
      "style": null,
      "media_id": null,
      "partner": null
    },
    "url": "/videos/6293412/klimaatactivisten-kleuren-kanaal-in-venetie-gifgroen.html",
    "open_new_window": false,
    "partner": null
  },
  {
    "id": 6293411,
    "slug": "lebron-james-verovert-met-los-angeles-lakers-eerste-editie-nba-cup",
    "type": "article",
    "title": "LeBron James verovert met Los Angeles Lakers eerste editie NBA Cup",
    "subtitle": null,
    "published_at": "2023-12-10T10:51:50+01:00",
    "updated_at": "2023-12-10T10:56:39+01:00",
    "media_id": "q6cxe4bankqb",
    "duration": null,
    "canonical_section": {
      "id": 1772456,
      "slug": "sport-overig",
      "type": "default",
      "name": "Sport Overig",
      "style": "nusport",
      "media_id": null,
      "partner": null
    },
    "url": "/sport-overig/6293411/lebron-james-verovert-met-los-angeles-lakers-eerste-editie-nba-cup.html",
    "open_new_window": false,
    "partner": null
  },
  {
    "id": 6293410,
    "slug": "goud-velzeboer-en-aflossingsploeg-in-peking-van-t-wout-twee-keer-onderuit",
    "type": "article",
    "title": "Goud Velzeboer en aflossingsploeg in Peking, Van 't Wout twee keer onderuit",
    "subtitle": null,
    "published_at": "2023-12-10T10:24:23+01:00",
    "updated_at": "2023-12-10T11:30:29+01:00",
    "media_id": "egdxhquami2x",
    "duration": null,
    "canonical_section": {
      "id": 1772452,
      "slug": "schaatsen",
      "type": "default",
      "name": "Schaatsen",
      "style": "nusport",
      "media_id": "5ktx9n6axubw",
      "partner": null
    },
    "url": "/schaatsen/6293410/goud-velzeboer-en-aflossingsploeg-in-peking-van-t-wout-twee-keer-onderuit.html",
    "open_new_window": false,
    "partner": null
  },
  {
    "id": 6293409,
    "slug": "bestuurder-overlijdt-nadat-auto-te-water-raakt-in-delft-passagier-zwaargewond",
    "type": "article",
    "title": "Bestuurder overlijdt nadat auto te water raakt in Delft, passagier zwaargewond",
    "subtitle": null,
    "published_at": "2023-12-10T10:12:11+01:00",
    "updated_at": "2023-12-10T11:00:32+01:00",
    "media_id": "bnbx33mab8fn",
    "duration": null,
    "canonical_section": {
      "id": 1771435,
      "slug": "binnenland",
      "type": "default",
      "name": "Binnenland",
      "style": "nu",
      "media_id": null,
      "partner": null
    },
    "url": "/binnenland/6293409/bestuurder-overlijdt-nadat-auto-te-water-raakt-in-delft-passagier-zwaargewond.html",
    "open_new_window": false,
    "partner": null
  },
  {
    "id": 6293408,
    "slug": "omstanders-filmen-dodelijke-tornado-in-vs",
    "type": "video",
    "title": "Omstanders filmen dodelijke tornado in VS",
    "subtitle": "Video",
    "published_at": "2023-12-10T10:06:25+01:00",
    "updated_at": "2023-12-10T10:06:27+01:00",
    "media_id": "ocnxgbtavt9r",
    "duration": "0:26",
    "canonical_section": {
      "id": 1772431,
      "slug": "videos",
      "type": "default",
      "name": "Video's",
      "style": null,
      "media_id": null,
      "partner": null
    },
    "url": "/videos/6293408/omstanders-filmen-dodelijke-tornado-in-vs.html",
    "open_new_window": false,
    "partner": null
  },
  {
    "id": 6293407,
    "slug": "topman-chipbedrijf-arm-uit-zorgen-over-verliezen-menselijke-controle-over-ai",
    "type": "article",
    "title": "Topman chipbedrijf Arm uit zorgen over verliezen menselijke controle over AI",
    "subtitle": null,
    "published_at": "2023-12-10T10:00:45+01:00",
    "updated_at": "2023-12-10T10:14:54+01:00",
    "media_id": "hc1xkkqaiq5q",
    "duration": null,
    "canonical_section": {
      "id": 1771438,
      "slug": "tech",
      "type": "default",
      "name": "Tech",
      "style": "nutech",
      "media_id": null,
      "partner": null
    },
    "url": "/tech/6293407/topman-chipbedrijf-arm-uit-zorgen-over-verliezen-menselijke-controle-over-ai.html",
    "open_new_window": false,
    "partner": null
  },
  {
    "id": 6293406,
    "slug": "jada-pinkett-klap-bij-oscar-uitreiking-redde-mijn-relatie-met-will-smith",
    "type": "article",
    "title": "Jada Pinkett: Klap bij Oscar-uitreiking redde mijn relatie met Will Smith",
    "subtitle": null,
    "published_at": "2023-12-10T09:55:47+01:00",
    "updated_at": "2023-12-10T10:00:14+01:00",
    "media_id": "uwfx3yravhus",
    "duration": null,
    "canonical_section": {
      "id": 125,
      "slug": "achterklap",
      "type": "default",
      "name": "Achterklap",
      "style": "nuentertainment",
      "media_id": null,
      "partner": null
    },
    "url": "/achterklap/6293406/jada-pinkett-klap-bij-oscar-uitreiking-redde-mijn-relatie-met-will-smith.html",
    "open_new_window": false,
    "partner": null
  },
  {
    "id": 6293405,
    "slug": "ohtani-troeft-messi-af-honkballer-tekent-recordcontract-van-650-miljoen-euro",
    "type": "article",
    "title": "Ohtani troeft Messi af: honkballer tekent recordcontract van 650 miljoen euro",
    "subtitle": null,
    "published_at": "2023-12-10T09:26:01+01:00",
    "updated_at": "2023-12-10T11:06:02+01:00",
    "media_id": "gg3xsrwausm9",
    "duration": null,
    "canonical_section": {
      "id": 1772456,
      "slug": "sport-overig",
      "type": "default",
      "name": "Sport Overig",
      "style": "nusport",
      "media_id": null,
      "partner": null
    },
    "url": "/sport-overig/6293405/ohtani-troeft-messi-af-honkballer-tekent-recordcontract-van-650-miljoen-euro.html",
    "open_new_window": false,
    "partner": null
  },
  {
    "id": 6293346,
    "slug": "positieve-en-moedige-reactie-op-onhoudbare-opvangsituatie",
    "type": "article",
    "title": "Positieve (en moedige) reactie op onhoudbare opvangsituatie",
    "subtitle": "Hoofdredactie",
    "published_at": "2023-12-10T09:03:39+01:00",
    "updated_at": "2023-12-10T11:27:56+01:00",
    "media_id": "fkkxpioaxk01",
    "duration": null,
    "canonical_section": {
      "id": 1772069,
      "slug": "blog",
      "type": "default",
      "name": "Van de hoofdredactie",
      "style": "nu",
      "media_id": null,
      "partner": null
    },
    "url": "/blog/6293346/positieve-en-moedige-reactie-op-onhoudbare-opvangsituatie.html",
    "open_new_window": false,
    "partner": null
  },
  {
    "id": 6293404,
    "slug": "anatomy-of-a-fall-verkozen-tot-beste-europese-film",
    "type": "article",
    "title": "Anatomy of a Fall verkozen tot beste Europese film",
    "subtitle": null,
    "published_at": "2023-12-10T09:02:33+01:00",
    "updated_at": "2023-12-10T09:10:32+01:00",
    "media_id": "s4oxn3yas0am",
    "duration": null,
    "canonical_section": {
      "id": 127,
      "slug": "film",
      "type": "default",
      "name": "Films & Series",
      "style": "nuuit",
      "media_id": null,
      "partner": null
    },
    "url": "/film/6293404/anatomy-of-a-fall-verkozen-tot-beste-europese-film.html",
    "open_new_window": false,
    "partner": null
  },
  {
    "id": 6293401,
    "slug": "grote-drukte-bij-de-egelopvang-meer-verzwakte-egels-dan-normaal",
    "type": "article",
    "title": "Grote drukte bij de egelopvang, meer verzwakte egels dan normaal",
    "subtitle": null,
    "published_at": "2023-12-10T07:54:18+01:00",
    "updated_at": "2023-12-10T10:24:47+01:00",
    "media_id": "3qox1juaiz07",
    "duration": null,
    "canonical_section": {
      "id": 1772536,
      "slug": "dieren",
      "type": "default",
      "name": "Dieren",
      "style": "nunjij",
      "media_id": null,
      "partner": null
    },
    "url": "/dieren/6293401/grote-drukte-bij-de-egelopvang-meer-verzwakte-egels-dan-normaal.html",
    "open_new_window": false,
    "partner": null
  },
  {
    "id": 6293397,
    "slug": "concerttour-eras-van-taylor-swift-levert-historisch-hoge-opbrengst-op",
    "type": "article",
    "title": "Concerttour Eras van Taylor Swift levert historisch hoge opbrengst op",
    "subtitle": null,
    "published_at": "2023-12-10T07:12:42+01:00",
    "updated_at": "2023-12-10T09:16:30+01:00",
    "media_id": "xl1xv8iav83e",
    "duration": null,
    "canonical_section": {
      "id": 868281,
      "slug": "muziek",
      "type": "default",
      "name": "Muziek",
      "style": "nuuit",
      "media_id": null,
      "partner": null
    },
    "url": "/muziek/6293397/concerttour-eras-van-taylor-swift-levert-historisch-hoge-opbrengst-op.html",
    "open_new_window": false,
    "partner": null
  },
  {
    "id": 6293395,
    "slug": "vanaf-vandaag-geldt-de-nieuwe-ns-dienstregeling-dit-is-er-veranderd",
    "type": "article",
    "title": "Vanaf vandaag geldt de nieuwe NS-dienstregeling: dit is er veranderd",
    "subtitle": null,
    "published_at": "2023-12-10T06:42:24+01:00",
    "updated_at": "2023-12-10T07:57:47+01:00",
    "media_id": "143xbgraczlu",
    "duration": null,
    "canonical_section": {
      "id": 1771435,
      "slug": "binnenland",
      "type": "default",
      "name": "Binnenland",
      "style": "nu",
      "media_id": null,
      "partner": null
    },
    "url": "/binnenland/6293395/vanaf-vandaag-geldt-de-nieuwe-ns-dienstregeling-dit-is-er-veranderd.html",
    "open_new_window": false,
    "partner": null
  },
  {
    "id": 6293394,
    "slug": "code-geel-in-noordelijke-kustgebieden-vanwege-zware-windstoten",
    "type": "article",
    "title": "Code geel in noordelijke kustgebieden vanwege zware windstoten",
    "subtitle": "Weerbericht",
    "published_at": "2023-12-10T06:22:02+01:00",
    "updated_at": "2023-12-10T09:33:04+01:00",
    "media_id": "i7jx6mzacz3b",
    "duration": null,
    "canonical_section": {
      "id": 1779283,
      "slug": "weerbericht",
      "type": "default",
      "name": "Weerbericht",
      "style": "nu",
      "media_id": null,
      "partner": null
    },
    "url": "/weerbericht/6293394/code-geel-in-noordelijke-kustgebieden-vanwege-zware-windstoten.html",
    "open_new_window": false,
    "partner": null
  },
  {
    "id": 6293393,
    "slug": "zes-doden-en-dik-twintig-gewonden-door-tornado-in-amerikaanse-staat-tennessee",
    "type": "article",
    "title": "Zes doden en dik twintig gewonden door tornado in Amerikaanse staat Tennessee",
    "subtitle": null,
    "published_at": "2023-12-10T05:55:52+01:00",
    "updated_at": "2023-12-10T10:16:13+01:00",
    "media_id": "c9fxwwpa2onr",
    "duration": null,
    "canonical_section": {
      "id": 1771436,
      "slug": "buitenland",
      "type": "default",
      "name": "Buitenland",
      "style": "nu",
      "media_id": null,
      "partner": null
    },
    "url": "/buitenland/6293393/zes-doden-en-dik-twintig-gewonden-door-tornado-in-amerikaanse-staat-tennessee.html",
    "open_new_window": false,
    "partner": null
  },
  {
    "id": 6293392,
    "slug": "het-woord-van-vandaag-raad-jij-het-woord-van-de-dag",
    "type": "article",
    "title": "Het Woord van vandaag: Raad jij het woord van de dag?",
    "subtitle": null,
    "published_at": "2023-12-10T05:18:28+01:00",
    "updated_at": "2023-12-10T05:18:29+01:00",
    "media_id": "vunx81iava32",
    "duration": null,
    "canonical_section": {
      "id": 1778843,
      "slug": "login-vereist",
      "type": "default",
      "name": "login-vereist",
      "style": "nu",
      "media_id": null,
      "partner": null
    },
    "url": "/login-vereist/6293392/het-woord-van-vandaag-raad-jij-het-woord-van-de-dag.html",
    "open_new_window": false,
    "partner": null
  },
  {
    "id": 6293390,
    "slug": "bijzonder-huwelijk-tussen-breakdance-en-spelen-is-het-10-jaar-te-vroeg",
    "type": "article",
    "title": "Bijzonder huwelijk tussen breakdance en Spelen: 'Is het 10 jaar te vroeg?'",
    "subtitle": "NU+",
    "published_at": "2023-12-10T05:10:05+01:00",
    "updated_at": "2023-12-10T08:31:56+01:00",
    "media_id": "o65x0yqazlqq",
    "duration": null,
    "canonical_section": {
      "id": 1772456,
      "slug": "sport-overig",
      "type": "default",
      "name": "Sport Overig",
      "style": "nusport",
      "media_id": null,
      "partner": null
    },
    "url": "/sport-overig/6293390/bijzonder-huwelijk-tussen-breakdance-en-spelen-is-het-10-jaar-te-vroeg.html",
    "open_new_window": false,
    "partner": null
  },
  {
    "id": 6293226,
    "slug": "moet-je-al-je-smarthomeapparaten-upgraden-naar-matter",
    "type": "article",
    "title": "Moet je al je smarthomeapparaten upgraden naar Matter?",
    "subtitle": "NU+",
    "published_at": "2023-12-10T05:06:30+01:00",
    "updated_at": "2023-12-10T05:06:31+01:00",
    "media_id": "h0dxe5mazjs2",
    "duration": null,
    "canonical_section": {
      "id": 1779328,
      "slug": "slimmer-leven",
      "type": "default",
      "name": "Slimmer leven",
      "style": "nutech",
      "media_id": null,
      "partner": null
    },
    "url": "/slimmer-leven/6293226/moet-je-al-je-smarthomeapparaten-upgraden-naar-matter.html",
    "open_new_window": false,
    "partner": null
  },
  {
    "id": 6293351,
    "slug": "kan-de-gek-zijn-beloftes-waarmaken-als-president-van-argentinie",
    "type": "article",
    "title": "Kan 'de Gek' zijn beloftes waarmaken als president van Argentinië?",
    "subtitle": "NU+",
    "published_at": "2023-12-10T05:05:39+01:00",
    "updated_at": "2023-12-10T05:05:40+01:00",
    "media_id": "ajzxwwjakbl0",
    "duration": null,
    "canonical_section": {
      "id": 1771436,
      "slug": "buitenland",
      "type": "default",
      "name": "Buitenland",
      "style": "nu",
      "media_id": null,
      "partner": null
    },
    "url": "/buitenland/6293351/kan-de-gek-zijn-beloftes-waarmaken-als-president-van-argentinie.html",
    "open_new_window": false,
    "partner": null
  },
  {
    "id": 6293236,
    "slug": "interview-collin-veijer-kansen-om-in-2024-kampioen-in-moto3-te-worden",
    "type": "article",
    "title": "Interview Collin Veijer: 'Kansen om in 2024 kampioen in Moto3 te worden'",
    "subtitle": "NU+",
    "published_at": "2023-12-10T05:03:56+01:00",
    "updated_at": "2023-12-10T11:07:33+01:00",
    "media_id": "tylx0j4afspy",
    "duration": null,
    "canonical_section": {
      "id": 1772456,
      "slug": "sport-overig",
      "type": "default",
      "name": "Sport Overig",
      "style": "nusport",
      "media_id": null,
      "partner": null
    },
    "url": "/sport-overig/6293236/interview-collin-veijer-kansen-om-in-2024-kampioen-in-moto3-te-worden.html",
    "open_new_window": false,
    "partner": null
  },
  {
    "id": 6293347,
    "slug": "dit-dorp-heeft-crisisopvang-juist-omarmd-echte-vriendschappen-ontstaan",
    "type": "article",
    "title": "Dit dorp heeft crisisopvang juist omarmd: 'Echte vriendschappen ontstaan'",
    "subtitle": "NU+",
    "published_at": "2023-12-10T05:02:53+01:00",
    "updated_at": "2023-12-10T09:06:08+01:00",
    "media_id": "hklxwh3a322t",
    "duration": null,
    "canonical_section": {
      "id": 1779003,
      "slug": "gebaseerd-op-jullie-vragen",
      "type": "default",
      "name": "Gebaseerd op NUjij",
      "style": "nu",
      "media_id": null,
      "partner": null
    },
    "url": "/gebaseerd-op-jullie-vragen/6293347/dit-dorp-heeft-crisisopvang-juist-omarmd-echte-vriendschappen-ontstaan.html",
    "open_new_window": false,
    "partner": null
  },
  {
    "id": 6293027,
    "slug": "verpleeghuiszorg-door-vergrijzing-niet-houdbaar-buiten-kaders-denken",
    "type": "article",
    "title": "Verpleeghuiszorg door vergrijzing niet houdbaar: 'Buiten kaders denken'",
    "subtitle": null,
    "published_at": "2023-12-10T05:02:04+01:00",
    "updated_at": "2023-12-10T08:23:03+01:00",
    "media_id": "cfrxtaba5khe",
    "duration": null,
    "canonical_section": {
      "id": 1771435,
      "slug": "binnenland",
      "type": "default",
      "name": "Binnenland",
      "style": "nu",
      "media_id": null,
      "partner": null
    },
    "url": "/binnenland/6293027/verpleeghuiszorg-door-vergrijzing-niet-houdbaar-buiten-kaders-denken.html",
    "open_new_window": false,
    "partner": null
  },
  {
    "id": 6293389,
    "slug": "landman-klopt-klaasen-en-is-eerste-nederlander-sinds-2017-in-lakeside-finale",
    "type": "article",
    "title": "Landman klopt Klaasen en is eerste Nederlander sinds 2017 in Lakeside-finale",
    "subtitle": null,
    "published_at": "2023-12-09T23:37:09+01:00",
    "updated_at": "2023-12-10T08:34:55+01:00",
    "media_id": "00xxa0fad5vt",
    "duration": null,
    "canonical_section": {
      "id": 1777376,
      "slug": "darts",
      "type": "default",
      "name": "Darts",
      "style": "nusport",
      "media_id": null,
      "partner": null
    },
    "url": "/darts/6293389/landman-klopt-klaasen-en-is-eerste-nederlander-sinds-2017-in-lakeside-finale.html",
    "open_new_window": false,
    "partner": null
  },
  {
    "id": 6293388,
    "slug": "az-boekt-ruime-zege-dankzij-fraaie-goals-de-wit-en-pavlidis-en-staat-weer-derde",
    "type": "article",
    "title": "AZ boekt ruime zege dankzij fraaie goals De Wit en Pavlidis en staat weer derde",
    "subtitle": null,
    "published_at": "2023-12-09T22:56:46+01:00",
    "updated_at": "2023-12-09T23:12:33+01:00",
    "media_id": "2ttxz44a10vc",
    "duration": null,
    "canonical_section": {
      "id": 1772338,
      "slug": "voetbal",
      "type": "default",
      "name": "Voetbal",
      "style": "nusport",
      "media_id": null,
      "partner": null
    },
    "url": "/voetbal/6293388/az-boekt-ruime-zege-dankzij-fraaie-goals-de-wit-en-pavlidis-en-staat-weer-derde.html",
    "open_new_window": false,
    "partner": null
  }
]
