[
  {
    "id": 6247825,
    "slug": "npo-ombudsman-onderzoekt-uitspraak-van-op1-presentatrice-gibbs-over-israel",
    "type": "article",
    "title": "NPO-ombudsman onderzoekt uitspraak van Op1-presentatrice Gibbs over Israël",
    "subtitle": null,
    "published_at": "2023-01-20T13:51:09+01:00",
    "updated_at": "2023-01-20T13:51:10+01:00",
    "media_id": "3q8x24na6itj",
    "duration": null,
    "canonical_section": {
      "id": 1771675,
      "slug": "media",
      "type": "default",
      "name": "Media",
      "style": "nuuit",
      "media_id": null,
      "partner": null
    },
    "url": "/media/6247825/npo-ombudsman-onderzoekt-uitspraak-van-op1-presentatrice-gibbs-over-israel.html",
    "open_new_window": false,
    "partner": null
  },
  {
    "id": 6247827,
    "slug": "haller-kan-zich-na-half-jaar-opmaken-voor-officieel-dortmund-debuut",
    "type": "article",
    "title": "Haller kan zich na half jaar opmaken voor officieel Dortmund-debuut",
    "subtitle": null,
    "published_at": "2023-01-20T13:50:19+01:00",
    "updated_at": "2023-01-20T13:50:20+01:00",
    "media_id": "jtsxz0ga88dz",
    "duration": null,
    "canonical_section": {
      "id": 1772338,
      "slug": "voetbal",
      "type": "default",
      "name": "Voetbal",
      "style": "nusport",
      "media_id": null,
      "partner": null
    },
    "url": "/voetbal/6247827/haller-kan-zich-na-half-jaar-opmaken-voor-officieel-dortmund-debuut.html",
    "open_new_window": false,
    "partner": null
  },
  {
    "id": 6247766,
    "slug": "flink-meer-meldingen-over-dierenleed-veel-via-oekrainers-met-gestrest-huisdier",
    "type": "article",
    "title": "Flink meer meldingen over dierenleed, veel via Oekraïners met gestrest huisdier",
    "subtitle": null,
    "published_at": "2023-01-20T13:41:16+01:00",
    "updated_at": "2023-01-20T13:56:44+01:00",
    "media_id": "arbxv4qat0o3",
    "duration": null,
    "canonical_section": {
      "id": 1771435,
      "slug": "binnenland",
      "type": "default",
      "name": "Binnenland",
      "style": "nu",
      "media_id": null,
      "partner": null
    },
    "url": "/binnenland/6247766/flink-meer-meldingen-over-dierenleed-veel-via-oekrainers-met-gestrest-huisdier.html",
    "open_new_window": false,
    "partner": null
  },
  {
    "id": 6247826,
    "slug": "bezoekers-hangen-ondersteboven-in-defecte-kermisattractie-in-china",
    "type": "video",
    "title": "Bezoekers hangen ondersteboven in defecte kermisattractie in China",
    "subtitle": "Video",
    "published_at": "2023-01-20T13:38:06+01:00",
    "updated_at": "2023-01-20T13:38:09+01:00",
    "media_id": "ztgxrjmaiqe3",
    "duration": "0:35",
    "canonical_section": {
      "id": 1771436,
      "slug": "buitenland",
      "type": "default",
      "name": "Buitenland",
      "style": "nu",
      "media_id": null,
      "partner": null
    },
    "url": "/buitenland/6247826/bezoekers-hangen-ondersteboven-in-defecte-kermisattractie-in-china.html",
    "open_new_window": false,
    "partner": null
  },
  {
    "id": 6247823,
    "slug": "files-door-winterweer-noord-brabant-minder-vliegtuigen-van-en-naar-eindhoven",
    "type": "article",
    "title": "Files door winterweer Noord-Brabant, minder vliegtuigen van en naar Eindhoven",
    "subtitle": null,
    "published_at": "2023-01-20T13:36:30+01:00",
    "updated_at": "2023-01-20T14:05:31+01:00",
    "media_id": "qz7xju7a5fvn",
    "duration": null,
    "canonical_section": {
      "id": 1771435,
      "slug": "binnenland",
      "type": "default",
      "name": "Binnenland",
      "style": "nu",
      "media_id": null,
      "partner": null
    },
    "url": "/binnenland/6247823/files-door-winterweer-noord-brabant-minder-vliegtuigen-van-en-naar-eindhoven.html",
    "open_new_window": false,
    "partner": null
  },
  {
    "id": 6247817,
    "slug": "van-nistelrooij-treurt-om-vertrek-madueke-maar-er-was-geen-weg-terug",
    "type": "article",
    "title": "Van Nistelrooij treurt om vertrek Madueke: 'Maar er was geen weg terug'",
    "subtitle": null,
    "published_at": "2023-01-20T13:27:24+01:00",
    "updated_at": "2023-01-20T13:27:26+01:00",
    "media_id": "959xhrvapasm",
    "duration": null,
    "canonical_section": {
      "id": 1772338,
      "slug": "voetbal",
      "type": "default",
      "name": "Voetbal",
      "style": "nusport",
      "media_id": null,
      "partner": null
    },
    "url": "/voetbal/6247817/van-nistelrooij-treurt-om-vertrek-madueke-maar-er-was-geen-weg-terug.html",
    "open_new_window": false,
    "partner": null
  },
  {
    "id": 6247818,
    "slug": "toch-doorstart-voor-failliete-medicijnfabriek-innogenerics-uit-leiden",
    "type": "article",
    "title": "Toch doorstart voor failliete medicijnfabriek InnoGenerics uit Leiden",
    "subtitle": null,
    "published_at": "2023-01-20T13:05:25+01:00",
    "updated_at": "2023-01-20T13:50:35+01:00",
    "media_id": "bavx5msanv11",
    "duration": null,
    "canonical_section": {
      "id": 1146768,
      "slug": "gezondheid",
      "type": "default",
      "name": "Gezondheid",
      "style": "nunjij",
      "media_id": null,
      "partner": null
    },
    "url": "/gezondheid/6247818/toch-doorstart-voor-failliete-medicijnfabriek-innogenerics-uit-leiden.html",
    "open_new_window": false,
    "partner": null
  },
  {
    "id": 6247816,
    "slug": "kouder-weer-zorgt-voor-meer-gasverbruik-en-legere-voorraden",
    "type": "article",
    "title": "Kouder weer zorgt voor meer gasverbruik en legere voorraden",
    "subtitle": null,
    "published_at": "2023-01-20T12:55:55+01:00",
    "updated_at": "2023-01-20T13:37:17+01:00",
    "media_id": "wigxnqhav09r",
    "duration": null,
    "canonical_section": {
      "id": 99,
      "slug": "economie",
      "type": "default",
      "name": "Economie",
      "style": "nuzakelijk",
      "media_id": null,
      "partner": null
    },
    "url": "/economie/6247816/kouder-weer-zorgt-voor-meer-gasverbruik-en-legere-voorraden.html",
    "open_new_window": false,
    "partner": null
  },
  {
    "id": 6247810,
    "slug": "minister-adema-met-spoed-naar-den-haag-voor-overleg-over-mestuitzondering",
    "type": "article",
    "title": "Minister Adema met spoed naar Den Haag voor overleg over mestuitzondering",
    "subtitle": null,
    "published_at": "2023-01-20T12:36:12+01:00",
    "updated_at": "2023-01-20T12:36:14+01:00",
    "media_id": "x78xvc3a8dv1",
    "duration": null,
    "canonical_section": {
      "id": 1771437,
      "slug": "politiek",
      "type": "default",
      "name": "Politiek",
      "style": "nu",
      "media_id": null,
      "partner": null
    },
    "url": "/politiek/6247810/minister-adema-met-spoed-naar-den-haag-voor-overleg-over-mestuitzondering.html",
    "open_new_window": false,
    "partner": null
  },
  {
    "id": 6247803,
    "slug": "dit-vinden-jullie-van-verbod-op-huisdieren-met-korte-snuit-of-vouworen-het-is-een-begin",
    "type": "article",
    "title": "Dit vinden jullie van verbod op huisdieren met korte snuit of vouworen: 'Het is een begin'",
    "subtitle": null,
    "published_at": "2023-01-20T12:32:13+01:00",
    "updated_at": "2023-01-20T12:32:14+01:00",
    "media_id": "lazx162aub63",
    "duration": null,
    "canonical_section": {
      "id": 1779134,
      "slug": "stelling",
      "type": "default",
      "name": "Stelling",
      "style": "nu",
      "media_id": null,
      "partner": null
    },
    "url": "/stelling/6247803/dit-vinden-jullie-van-verbod-op-huisdieren-met-korte-snuit-of-vouworen-het-is-een-begin.html",
    "open_new_window": false,
    "partner": null
  },
  {
    "id": 6247686,
    "slug": "is-een-thuisbatterij-om-zonnestroom-op-te-slaan-een-goed-idee",
    "type": "article",
    "title": "Is een thuisbatterij om zonnestroom op te slaan een goed idee?",
    "subtitle": "NU+",
    "published_at": "2023-01-20T12:10:46+01:00",
    "updated_at": "2023-01-20T12:15:37+01:00",
    "media_id": "a23x7ahaidgb",
    "duration": null,
    "canonical_section": {
      "id": 1772342,
      "slug": "wonen",
      "type": "default",
      "name": "Wonen",
      "style": "nuzakelijk",
      "media_id": "3qlxtaiahydl",
      "partner": null
    },
    "url": "/wonen/6247686/is-een-thuisbatterij-om-zonnestroom-op-te-slaan-een-goed-idee.html",
    "open_new_window": false,
    "partner": null
  },
  {
    "id": 6247812,
    "slug": "rechter-legt-willem-engel-voorwaardelijke-celstraf-op",
    "type": "video",
    "title": "Rechter legt Willem Engel voorwaardelijke celstraf op",
    "subtitle": "Video",
    "published_at": "2023-01-20T12:10:43+01:00",
    "updated_at": "2023-01-20T12:10:44+01:00",
    "media_id": "0m9xujfaskq5",
    "duration": "0:53",
    "canonical_section": {
      "id": 1771435,
      "slug": "binnenland",
      "type": "default",
      "name": "Binnenland",
      "style": "nu",
      "media_id": null,
      "partner": null
    },
    "url": "/binnenland/6247812/rechter-legt-willem-engel-voorwaardelijke-celstraf-op.html",
    "open_new_window": false,
    "partner": null
  },
  {
    "id": 6247809,
    "slug": "politie-houdt-elf-leden-van-harde-kern-feyenoord-aan-voor-onder-meer-intimidatie",
    "type": "article",
    "title": "Politie houdt elf leden van harde kern Feyenoord aan voor onder meer intimidatie",
    "subtitle": null,
    "published_at": "2023-01-20T12:08:18+01:00",
    "updated_at": "2023-01-20T12:41:57+01:00",
    "media_id": "jcyxyjwamjzh",
    "duration": null,
    "canonical_section": {
      "id": 1771435,
      "slug": "binnenland",
      "type": "default",
      "name": "Binnenland",
      "style": "nu",
      "media_id": null,
      "partner": null
    },
    "url": "/binnenland/6247809/politie-houdt-elf-leden-van-harde-kern-feyenoord-aan-voor-onder-meer-intimidatie.html",
    "open_new_window": false,
    "partner": null
  },
  {
    "id": 6247791,
    "slug": "werknemers-slaan-oproepen-rijkswaterstaat-over-thuiswerken-in-de-wind",
    "type": "article",
    "title": "Werknemers slaan oproepen Rijkswaterstaat over thuiswerken in de wind",
    "subtitle": null,
    "published_at": "2023-01-20T12:05:52+01:00",
    "updated_at": "2023-01-20T13:45:38+01:00",
    "media_id": "bdrxucranf9r",
    "duration": null,
    "canonical_section": {
      "id": 99,
      "slug": "economie",
      "type": "default",
      "name": "Economie",
      "style": "nuzakelijk",
      "media_id": null,
      "partner": null
    },
    "url": "/economie/6247791/werknemers-slaan-oproepen-rijkswaterstaat-over-thuiswerken-in-de-wind.html",
    "open_new_window": false,
    "partner": null
  },
  {
    "id": 6247802,
    "slug": "staatsschuld-vs-tikt-weer-plafond-aan-regering-doet-noodgrepen",
    "type": "article",
    "title": "Staatsschuld VS tikt weer plafond aan, regering doet noodgrepen",
    "subtitle": null,
    "published_at": "2023-01-20T12:03:26+01:00",
    "updated_at": "2023-01-20T12:03:27+01:00",
    "media_id": "dfax32ian1rn",
    "duration": null,
    "canonical_section": {
      "id": 99,
      "slug": "economie",
      "type": "default",
      "name": "Economie",
      "style": "nuzakelijk",
      "media_id": null,
      "partner": null
    },
    "url": "/economie/6247802/staatsschuld-vs-tikt-weer-plafond-aan-regering-doet-noodgrepen.html",
    "open_new_window": false,
    "partner": null
  },
  {
    "id": 6247806,
    "slug": "twaalfduizend-banen-op-de-tocht-bij-google-moederbedrijf-alphabet",
    "type": "article",
    "title": "Twaalfduizend banen op de tocht bij Google-moederbedrijf Alphabet",
    "subtitle": null,
    "published_at": "2023-01-20T11:55:33+01:00",
    "updated_at": "2023-01-20T13:46:37+01:00",
    "media_id": "t3fxdvnagesp",
    "duration": null,
    "canonical_section": {
      "id": 1771438,
      "slug": "tech",
      "type": "default",
      "name": "Tech",
      "style": "nutech",
      "media_id": null,
      "partner": null
    },
    "url": "/tech/6247806/twaalfduizend-banen-op-de-tocht-bij-google-moederbedrijf-alphabet.html",
    "open_new_window": false,
    "partner": null
  },
  {
    "id": 6247798,
    "slug": "voetballer-dani-alves-in-barcelona-gearresteerd-op-verdenking-van-aanranding",
    "type": "article",
    "title": "Voetballer Dani Alves in Barcelona gearresteerd op verdenking van aanranding",
    "subtitle": null,
    "published_at": "2023-01-20T11:53:27+01:00",
    "updated_at": "2023-01-20T13:28:25+01:00",
    "media_id": "k9gx4d1a3kw2",
    "duration": null,
    "canonical_section": {
      "id": 1772338,
      "slug": "voetbal",
      "type": "default",
      "name": "Voetbal",
      "style": "nusport",
      "media_id": null,
      "partner": null
    },
    "url": "/voetbal/6247798/voetballer-dani-alves-in-barcelona-gearresteerd-op-verdenking-van-aanranding.html",
    "open_new_window": false,
    "partner": null
  },
  {
    "id": 6247797,
    "slug": "willem-engel-grotendeels-vrijgesproken-maand-voorwaardelijk-vanwege-opruiing",
    "type": "article",
    "title": "Willem Engel grotendeels vrijgesproken: maand voorwaardelijk vanwege opruiing",
    "subtitle": null,
    "published_at": "2023-01-20T11:51:12+01:00",
    "updated_at": "2023-01-20T12:47:55+01:00",
    "media_id": "2gkx8biac08r",
    "duration": null,
    "canonical_section": {
      "id": 1771435,
      "slug": "binnenland",
      "type": "default",
      "name": "Binnenland",
      "style": "nu",
      "media_id": null,
      "partner": null
    },
    "url": "/binnenland/6247797/willem-engel-grotendeels-vrijgesproken-maand-voorwaardelijk-vanwege-opruiing.html",
    "open_new_window": false,
    "partner": null
  },
  {
    "id": 6247793,
    "slug": "nos-correspondent-mustafa-marghadi-aangereden-door-vrachtwagen",
    "type": "article",
    "title": "NOS-correspondent Mustafa Marghadi aangereden door vrachtwagen",
    "subtitle": null,
    "published_at": "2023-01-20T11:38:22+01:00",
    "updated_at": "2023-01-20T11:41:29+01:00",
    "media_id": "6mkxu5kapq89",
    "duration": null,
    "canonical_section": {
      "id": 125,
      "slug": "achterklap",
      "type": "default",
      "name": "Achterklap",
      "style": "nuentertainment",
      "media_id": null,
      "partner": null
    },
    "url": "/achterklap/6247793/nos-correspondent-mustafa-marghadi-aangereden-door-vrachtwagen.html",
    "open_new_window": false,
    "partner": null
  },
  {
    "id": 6247792,
    "slug": "frits-spits-is-gedotterd-en-komende-weken-niet-te-horen-op-de-radio",
    "type": "article",
    "title": "Frits Spits is gedotterd en komende weken niet te horen op de radio",
    "subtitle": null,
    "published_at": "2023-01-20T11:20:56+01:00",
    "updated_at": "2023-01-20T14:00:53+01:00",
    "media_id": "4ywxgkoae3fd",
    "duration": null,
    "canonical_section": {
      "id": 125,
      "slug": "achterklap",
      "type": "default",
      "name": "Achterklap",
      "style": "nuentertainment",
      "media_id": null,
      "partner": null
    },
    "url": "/achterklap/6247792/frits-spits-is-gedotterd-en-komende-weken-niet-te-horen-op-de-radio.html",
    "open_new_window": false,
    "partner": null
  },
  {
    "id": 6247787,
    "slug": "grootste-pad-ooit-ontdekt-in-australie-voetbal-met-pootjes-van-bijna-3-kilo",
    "type": "article",
    "title": "Grootste pad ooit ontdekt in Australië: 'Voetbal met pootjes' van bijna 3 kilo",
    "subtitle": null,
    "published_at": "2023-01-20T11:18:04+01:00",
    "updated_at": "2023-01-20T12:26:47+01:00",
    "media_id": "fi4xiura2wx4",
    "duration": null,
    "canonical_section": {
      "id": 1772536,
      "slug": "dieren",
      "type": "default",
      "name": "Dieren",
      "style": "nunjij",
      "media_id": null,
      "partner": null
    },
    "url": "/dieren/6247787/grootste-pad-ooit-ontdekt-in-australie-voetbal-met-pootjes-van-bijna-3-kilo.html",
    "open_new_window": false,
    "partner": null
  },
  {
    "id": 6247775,
    "slug": "minister-wil-verbod-op-houden-van-honden-met-korte-snuit-en-katten-met-vouworen",
    "type": "article",
    "title": "Minister wil verbod op houden van honden met korte snuit en katten met vouworen",
    "subtitle": null,
    "published_at": "2023-01-20T11:11:45+01:00",
    "updated_at": "2023-01-20T13:06:39+01:00",
    "media_id": "savxycyaoj87",
    "duration": null,
    "canonical_section": {
      "id": 1771435,
      "slug": "binnenland",
      "type": "default",
      "name": "Binnenland",
      "style": "nu",
      "media_id": null,
      "partner": null
    },
    "url": "/binnenland/6247775/minister-wil-verbod-op-houden-van-honden-met-korte-snuit-en-katten-met-vouworen.html",
    "open_new_window": false,
    "partner": null
  },
  {
    "id": 6247781,
    "slug": "madonna-doet-twee-concerten-in-ziggo-dome-wegens-grote-belangstelling",
    "type": "article",
    "title": "Madonna doet twee concerten in Ziggo Dome wegens grote belangstelling",
    "subtitle": null,
    "published_at": "2023-01-20T11:06:19+01:00",
    "updated_at": "2023-01-20T12:08:12+01:00",
    "media_id": "89uxgxbaoiah",
    "duration": null,
    "canonical_section": {
      "id": 868281,
      "slug": "muziek",
      "type": "default",
      "name": "Muziek",
      "style": "nuuit",
      "media_id": null,
      "partner": null
    },
    "url": "/muziek/6247781/madonna-doet-twee-concerten-in-ziggo-dome-wegens-grote-belangstelling.html",
    "open_new_window": false,
    "partner": null
  },
  {
    "id": 6247785,
    "slug": "sneeuwval-tovert-deel-van-nederland-om-in-winterwonderland",
    "type": "video",
    "title": "Sneeuwval tovert deel van Nederland om in winterwonderland",
    "subtitle": "Video",
    "published_at": "2023-01-20T10:56:49+01:00",
    "updated_at": "2023-01-20T11:52:49+01:00",
    "media_id": "umlxb4kalriz",
    "duration": "0:37",
    "canonical_section": {
      "id": 1771435,
      "slug": "binnenland",
      "type": "default",
      "name": "Binnenland",
      "style": "nu",
      "media_id": null,
      "partner": null
    },
    "url": "/binnenland/6247785/sneeuwval-tovert-deel-van-nederland-om-in-winterwonderland.html",
    "open_new_window": false,
    "partner": null
  },
  {
    "id": 6247784,
    "slug": "rangers-vinden-gigantische-reuzenpad-in-australie",
    "type": "video",
    "title": "Rangers vinden gigantische reuzenpad in Australië",
    "subtitle": "Video",
    "published_at": "2023-01-20T10:51:52+01:00",
    "updated_at": "2023-01-20T10:52:07+01:00",
    "media_id": "5ovxxftax8g9",
    "duration": "0:41",
    "canonical_section": {
      "id": 1772536,
      "slug": "dieren",
      "type": "default",
      "name": "Dieren",
      "style": "nunjij",
      "media_id": null,
      "partner": null
    },
    "url": "/dieren/6247784/rangers-vinden-gigantische-reuzenpad-in-australie.html",
    "open_new_window": false,
    "partner": null
  },
  {
    "id": 6247776,
    "slug": "ryanair-op-vingers-getikt-door-acm-vanwege-duurzaamheidsclaim",
    "type": "article",
    "title": "Ryanair op vingers getikt door ACM vanwege duurzaamheidsclaim",
    "subtitle": null,
    "published_at": "2023-01-20T10:43:55+01:00",
    "updated_at": "2023-01-20T10:45:02+01:00",
    "media_id": "xyexoe1aqlse",
    "duration": null,
    "canonical_section": {
      "id": 99,
      "slug": "economie",
      "type": "default",
      "name": "Economie",
      "style": "nuzakelijk",
      "media_id": null,
      "partner": null
    },
    "url": "/economie/6247776/ryanair-op-vingers-getikt-door-acm-vanwege-duurzaamheidsclaim.html",
    "open_new_window": false,
    "partner": null
  },
  {
    "id": 6247774,
    "slug": "bijna-25-miljoen-bezoekers-meer-voor-concerten-en-festivals-dan-in-2019",
    "type": "article",
    "title": "Bijna 2,5 miljoen bezoekers meer voor concerten en festivals dan in 2019",
    "subtitle": null,
    "published_at": "2023-01-20T10:31:43+01:00",
    "updated_at": "2023-01-20T10:31:44+01:00",
    "media_id": "1krx1iiav4uv",
    "duration": null,
    "canonical_section": {
      "id": 868281,
      "slug": "muziek",
      "type": "default",
      "name": "Muziek",
      "style": "nuuit",
      "media_id": null,
      "partner": null
    },
    "url": "/muziek/6247774/bijna-25-miljoen-bezoekers-meer-voor-concerten-en-festivals-dan-in-2019.html",
    "open_new_window": false,
    "partner": null
  },
  {
    "id": 6247761,
    "slug": "uitzending-met-andre-hazes-best-bekeken-jinek-aflevering-van-de-week",
    "type": "article",
    "title": "Uitzending met André Hazes best bekeken Jinek-aflevering van de week",
    "subtitle": null,
    "published_at": "2023-01-20T10:18:27+01:00",
    "updated_at": "2023-01-20T10:18:28+01:00",
    "media_id": "9itx4phaezme",
    "duration": null,
    "canonical_section": {
      "id": 1771675,
      "slug": "media",
      "type": "default",
      "name": "Media",
      "style": "nuuit",
      "media_id": null,
      "partner": null
    },
    "url": "/media/6247761/uitzending-met-andre-hazes-best-bekeken-jinek-aflevering-van-de-week.html",
    "open_new_window": false,
    "partner": null
  },
  {
    "id": 6247772,
    "slug": "rijimpressie-lucid-air",
    "type": "video",
    "title": "Rijimpressie: Lucid Air",
    "subtitle": "Video",
    "published_at": "2023-01-20T10:13:34+01:00",
    "updated_at": "2023-01-20T10:13:35+01:00",
    "media_id": "60axbpeavkvh",
    "duration": "12:43",
    "canonical_section": {
      "id": 881569,
      "slug": "auto",
      "type": "default",
      "name": "Onderweg",
      "style": "nuzakelijk",
      "media_id": "z66x61xaq79c",
      "partner": null
    },
    "url": "/auto/6247772/rijimpressie-lucid-air.html",
    "open_new_window": false,
    "partner": null
  },
  {
    "id": 6247769,
    "slug": "tim-hofman-door-villamedia-uitgeroepen-tot-journalist-van-het-jaar",
    "type": "article",
    "title": "Tim Hofman door Villamedia uitgeroepen tot Journalist van het Jaar",
    "subtitle": null,
    "published_at": "2023-01-20T10:07:51+01:00",
    "updated_at": "2023-01-20T12:16:41+01:00",
    "media_id": "g3zxx1sad3nb",
    "duration": null,
    "canonical_section": {
      "id": 1771675,
      "slug": "media",
      "type": "default",
      "name": "Media",
      "style": "nuuit",
      "media_id": null,
      "partner": null
    },
    "url": "/media/6247769/tim-hofman-door-villamedia-uitgeroepen-tot-journalist-van-het-jaar.html",
    "open_new_window": false,
    "partner": null
  }
]
