[
  {
    "id": 6270881,
    "slug": "weerbericht-je-kan-vandaag-beter-je-regenjas-meenemen-dan-je-paraplu",
    "type": "article",
    "title": "Weerbericht: Je kan vandaag beter je regenjas meenemen dan je paraplu",
    "subtitle": null,
    "published_at": "2023-07-05T05:34:21+02:00",
    "updated_at": "2023-07-05T05:34:23+02:00",
    "media_id": "0xbxatqa0kd8",
    "duration": null,
    "canonical_section": {
      "id": 1771435,
      "slug": "binnenland",
      "type": "default",
      "name": "Binnenland",
      "style": "nu",
      "media_id": null,
      "partner": null
    },
    "url": "/binnenland/6270881/weerbericht-je-kan-vandaag-beter-je-regenjas-meenemen-dan-je-paraplu.html",
    "open_new_window": false,
    "partner": null
  },
  {
    "id": 6270880,
    "slug": "volg-hier-hoe-nederland-zich-schrap-zet-voor-storm-poly",
    "type": "article",
    "title": "Volg hier hoe Nederland zich schrap zet voor storm Poly",
    "subtitle": "Liveblog",
    "published_at": "2023-07-05T05:20:28+02:00",
    "updated_at": "2023-07-05T05:40:43+02:00",
    "media_id": "1ykxzpmaup4l",
    "duration": null,
    "canonical_section": {
      "id": 1771435,
      "slug": "binnenland",
      "type": "default",
      "name": "Binnenland",
      "style": "nu",
      "media_id": null,
      "partner": null
    },
    "url": "/binnenland/6270880/volg-hier-hoe-nederland-zich-schrap-zet-voor-storm-poly.html",
    "open_new_window": false,
    "partner": null
  },
  {
    "id": 6270652,
    "slug": "festival-of-museumbezoek-is-knap-lastig-als-je-prikkelgevoelig-bent",
    "type": "article",
    "title": "Festival- of museumbezoek is knap lastig als je prikkelgevoelig bent",
    "subtitle": "NU+",
    "published_at": "2023-07-05T05:10:11+02:00",
    "updated_at": "2023-07-05T05:10:13+02:00",
    "media_id": "nprxiqpans5e",
    "duration": null,
    "canonical_section": {
      "id": 868281,
      "slug": "muziek",
      "type": "default",
      "name": "Muziek",
      "style": "nuuit",
      "media_id": null,
      "partner": null
    },
    "url": "/muziek/6270652/festival-of-museumbezoek-is-knap-lastig-als-je-prikkelgevoelig-bent.html",
    "open_new_window": false,
    "partner": null
  },
  {
    "id": 6270861,
    "slug": "ook-op-een-circuit-is-sprinten-in-de-tour-chaotisch-het-was-supergevaarlijk",
    "type": "article",
    "title": "Ook op een circuit is sprinten in de Tour chaotisch: 'Het was supergevaarlijk'",
    "subtitle": null,
    "published_at": "2023-07-05T05:06:24+02:00",
    "updated_at": "2023-07-05T05:06:25+02:00",
    "media_id": "l7txvwracwu2",
    "duration": null,
    "canonical_section": {
      "id": 1772173,
      "slug": "tour-de-france",
      "type": "default",
      "name": "Tour de France",
      "style": "nusport",
      "media_id": null,
      "partner": null
    },
    "url": "/tour-de-france/6270861/ook-op-een-circuit-is-sprinten-in-de-tour-chaotisch-het-was-supergevaarlijk.html",
    "open_new_window": false,
    "partner": null
  },
  {
    "id": 6270839,
    "slug": "duur-gas-zorgde-in-2022-voor-laagste-energieverbruik-in-dertig-jaar",
    "type": "article",
    "title": "Duur gas zorgde in 2022 voor laagste energieverbruik in dertig jaar",
    "subtitle": null,
    "published_at": "2023-07-05T05:04:39+02:00",
    "updated_at": "2023-07-05T05:04:41+02:00",
    "media_id": "nk7x310aajuv",
    "duration": null,
    "canonical_section": {
      "id": 99,
      "slug": "economie",
      "type": "default",
      "name": "Economie",
      "style": "nuzakelijk",
      "media_id": null,
      "partner": null
    },
    "url": "/economie/6270839/duur-gas-zorgde-in-2022-voor-laagste-energieverbruik-in-dertig-jaar.html",
    "open_new_window": false,
    "partner": null
  },
  {
    "id": 6270684,
    "slug": "achter-de-oorlog-in-een-ecologische-ramp-vrezen-voor-een-nucleaire",
    "type": "article",
    "title": "Achter de oorlog: In een ecologische ramp vrezen voor een nucleaire",
    "subtitle": "NU+",
    "published_at": "2023-07-05T05:02:02+02:00",
    "updated_at": "2023-07-05T05:02:03+02:00",
    "media_id": "b1gxwb7apbn1",
    "duration": null,
    "canonical_section": {
      "id": 1778980,
      "slug": "spanningen-oekraine",
      "type": "default",
      "name": "Oorlog in Oekraïne",
      "style": "nu",
      "media_id": null,
      "partner": null
    },
    "url": "/spanningen-oekraine/6270684/achter-de-oorlog-in-een-ecologische-ramp-vrezen-voor-een-nucleaire.html",
    "open_new_window": false,
    "partner": null
  },
  {
    "id": 6270828,
    "slug": "strijd-om-hogere-lonen-wordt-komende-maanden-nog-harder",
    "type": "article",
    "title": "Strijd om hogere lonen wordt komende maanden nog harder",
    "subtitle": null,
    "published_at": "2023-07-05T05:01:05+02:00",
    "updated_at": "2023-07-05T05:01:07+02:00",
    "media_id": "xyux3gkaa4fe",
    "duration": null,
    "canonical_section": {
      "id": 99,
      "slug": "economie",
      "type": "default",
      "name": "Economie",
      "style": "nuzakelijk",
      "media_id": null,
      "partner": null
    },
    "url": "/economie/6270828/strijd-om-hogere-lonen-wordt-komende-maanden-nog-harder.html",
    "open_new_window": false,
    "partner": null
  },
  {
    "id": 6270799,
    "slug": "mensen-houden-gemiddeld-meer-geld-over-toch-grotere-groep-in-het-nauw",
    "type": "article",
    "title": "Mensen houden gemiddeld meer geld over, toch grotere groep in het nauw",
    "subtitle": null,
    "published_at": "2023-07-05T05:00:19+02:00",
    "updated_at": "2023-07-05T05:06:59+02:00",
    "media_id": "74mxvu2aydfc",
    "duration": null,
    "canonical_section": {
      "id": 99,
      "slug": "economie",
      "type": "default",
      "name": "Economie",
      "style": "nuzakelijk",
      "media_id": null,
      "partner": null
    },
    "url": "/economie/6270799/mensen-houden-gemiddeld-meer-geld-over-toch-grotere-groep-in-het-nauw.html",
    "open_new_window": false,
    "partner": null
  },
  {
    "id": 6270879,
    "slug": "knmi-waarschuwt-voor-storm-poly-code-oranje-om-zeer-zware-windstoten",
    "type": "article",
    "title": "KNMI waarschuwt voor storm Poly: code oranje om zeer zware windstoten",
    "subtitle": null,
    "published_at": "2023-07-05T04:31:33+02:00",
    "updated_at": "2023-07-05T06:00:57+02:00",
    "media_id": "2yoxvz6aoe3s",
    "duration": null,
    "canonical_section": {
      "id": 1771435,
      "slug": "binnenland",
      "type": "default",
      "name": "Binnenland",
      "style": "nu",
      "media_id": null,
      "partner": null
    },
    "url": "/binnenland/6270879/knmi-waarschuwt-voor-storm-poly-code-oranje-om-zeer-zware-windstoten.html",
    "open_new_window": false,
    "partner": null
  },
  {
    "id": 6270878,
    "slug": "jetten-waarschuwt-kabinet-kan-klimaatmiljarden-ook-zonder-fonds-uitgeven",
    "type": "article",
    "title": "Jetten waarschuwt: kabinet kan klimaatmiljarden ook zonder fonds uitgeven",
    "subtitle": null,
    "published_at": "2023-07-05T01:43:27+02:00",
    "updated_at": "2023-07-05T01:43:29+02:00",
    "media_id": "phpxsavajnnn",
    "duration": null,
    "canonical_section": {
      "id": 1771437,
      "slug": "politiek",
      "type": "default",
      "name": "Politiek",
      "style": "nu",
      "media_id": null,
      "partner": null
    },
    "url": "/politiek/6270878/jetten-waarschuwt-kabinet-kan-klimaatmiljarden-ook-zonder-fonds-uitgeven.html",
    "open_new_window": false,
    "partner": null
  },
  {
    "id": 6270877,
    "slug": "daniel-radcliffe-denkt-dat-nieuwe-harry-potter-serie-hem-niet-nodig-heeft",
    "type": "article",
    "title": "Daniel Radcliffe denkt dat nieuwe Harry Potter-serie hem niet nodig heeft",
    "subtitle": null,
    "published_at": "2023-07-04T23:53:31+02:00",
    "updated_at": "2023-07-04T23:54:44+02:00",
    "media_id": "qmdxvqwaziyy",
    "duration": null,
    "canonical_section": {
      "id": 1772242,
      "slug": "entertainment",
      "type": "default",
      "name": "Media en Cultuur",
      "style": "nuuit",
      "media_id": null,
      "partner": null
    },
    "url": "/entertainment/6270877/daniel-radcliffe-denkt-dat-nieuwe-harry-potter-serie-hem-niet-nodig-heeft.html",
    "open_new_window": false,
    "partner": null
  },
  {
    "id": 6270875,
    "slug": "firmino-is-na-vertrek-bij-liverpool-volgende-topspeler-die-voor-saoedi-arabie-kiest",
    "type": "article",
    "title": "Firmino is na vertrek bij Liverpool volgende topspeler die voor Saoedi-Arabië kiest",
    "subtitle": null,
    "published_at": "2023-07-04T23:38:38+02:00",
    "updated_at": "2023-07-04T23:42:41+02:00",
    "media_id": "g51xo9lawhx0",
    "duration": null,
    "canonical_section": {
      "id": 1772338,
      "slug": "voetbal",
      "type": "default",
      "name": "Voetbal",
      "style": "nusport",
      "media_id": null,
      "partner": null
    },
    "url": "/voetbal/6270875/firmino-is-na-vertrek-bij-liverpool-volgende-topspeler-die-voor-saoedi-arabie-kiest.html",
    "open_new_window": false,
    "partner": null
  },
  {
    "id": 6270873,
    "slug": "murray-genoot-van-steun-federer-laatste-keer-supporterde-hij-nog-tegen-mij",
    "type": "article",
    "title": "Murray genoot van steun Federer: 'Laatste keer supporterde hij nog tegen mij'",
    "subtitle": null,
    "published_at": "2023-07-04T23:09:46+02:00",
    "updated_at": "2023-07-04T23:11:54+02:00",
    "media_id": "3ryxp88ashig",
    "duration": null,
    "canonical_section": {
      "id": 1772432,
      "slug": "tennis",
      "type": "default",
      "name": "Tennis",
      "style": "nusport",
      "media_id": "m1oxohpan0gq",
      "partner": null
    },
    "url": "/tennis/6270873/murray-genoot-van-steun-federer-laatste-keer-supporterde-hij-nog-tegen-mij.html",
    "open_new_window": false,
    "partner": null
  },
  {
    "id": 6270872,
    "slug": "mount-vertrekt-na-achttien-jaar-bij-chelsea-en-lijkt-op-weg-naar-united-van-ten-hag",
    "type": "article",
    "title": "Mount vertrekt na achttien jaar bij Chelsea en lijkt op weg naar United van Ten Hag",
    "subtitle": null,
    "published_at": "2023-07-04T22:48:28+02:00",
    "updated_at": "2023-07-04T22:53:51+02:00",
    "media_id": "yc4x2kxataru",
    "duration": null,
    "canonical_section": {
      "id": 1772338,
      "slug": "voetbal",
      "type": "default",
      "name": "Voetbal",
      "style": "nusport",
      "media_id": null,
      "partner": null
    },
    "url": "/voetbal/6270872/mount-vertrekt-na-achttien-jaar-bij-chelsea-en-lijkt-op-weg-naar-united-van-ten-hag.html",
    "open_new_window": false,
    "partner": null
  },
  {
    "id": 6270871,
    "slug": "zeeleeuw-valt-van-zwembadrand-boven-op-trainer-op-mallorca",
    "type": "video",
    "title": "Zeeleeuw valt van zwembadrand boven op trainer op Mallorca",
    "subtitle": "Video",
    "published_at": "2023-07-04T22:34:07+02:00",
    "updated_at": "2023-07-04T22:34:58+02:00",
    "media_id": "cd4xqexaoqsr",
    "duration": "0:29",
    "canonical_section": {
      "id": 1772431,
      "slug": "videos",
      "type": "default",
      "name": "Video's",
      "style": null,
      "media_id": null,
      "partner": null
    },
    "url": "/videos/6270871/zeeleeuw-valt-van-zwembadrand-boven-op-trainer-op-mallorca.html",
    "open_new_window": false,
    "partner": null
  },
  {
    "id": 6270869,
    "slug": "hockeyers-veroveren-opnieuw-titel-in-pro-league-na-overwinning-op-belgie",
    "type": "article",
    "title": "Hockeyers veroveren opnieuw titel in Pro League na overwinning op België",
    "subtitle": null,
    "published_at": "2023-07-04T22:10:12+02:00",
    "updated_at": "2023-07-04T22:56:55+02:00",
    "media_id": "ppqxfupawv8h",
    "duration": null,
    "canonical_section": {
      "id": 1772456,
      "slug": "sport-overig",
      "type": "default",
      "name": "Sport Overig",
      "style": "nusport",
      "media_id": null,
      "partner": null
    },
    "url": "/sport-overig/6270869/hockeyers-veroveren-opnieuw-titel-in-pro-league-na-overwinning-op-belgie.html",
    "open_new_window": false,
    "partner": null
  },
  {
    "id": 6270848,
    "slug": "frankrijk-verdeeld-over-rellen-veel-steun-voor-agent-en-nabestaanden-tiener",
    "type": "article",
    "title": "Frankrijk verdeeld over rellen: veel steun voor agent en nabestaanden tiener",
    "subtitle": null,
    "published_at": "2023-07-04T22:05:10+02:00",
    "updated_at": "2023-07-04T22:21:40+02:00",
    "media_id": "7mtxyoaa37yn",
    "duration": null,
    "canonical_section": {
      "id": 1779258,
      "slug": "binnenland-en-buitenland",
      "type": "default",
      "name": "Binnen- en buitenland",
      "style": "nu",
      "media_id": null,
      "partner": null
    },
    "url": "/binnenland-en-buitenland/6270848/frankrijk-verdeeld-over-rellen-veel-steun-voor-agent-en-nabestaanden-tiener.html",
    "open_new_window": false,
    "partner": null
  },
  {
    "id": 6270867,
    "slug": "samenvatting-jakobsen-komt-ten-val-in-chaotische-finale-tour",
    "type": "video",
    "title": "Samenvatting: Jakobsen komt ten val in chaotische finale Tour",
    "subtitle": "Video",
    "published_at": "2023-07-04T21:34:33+02:00",
    "updated_at": "2023-07-04T21:34:35+02:00",
    "media_id": "ccsx2yqa4vvb",
    "duration": "2:40",
    "canonical_section": {
      "id": 1772173,
      "slug": "tour-de-france",
      "type": "default",
      "name": "Tour de France",
      "style": "nusport",
      "media_id": null,
      "partner": null
    },
    "url": "/tour-de-france/6270867/samenvatting-jakobsen-komt-ten-val-in-chaotische-finale-tour.html",
    "open_new_window": false,
    "partner": null
  },
  {
    "id": 6270866,
    "slug": "belgische-koning-albert-mag-woensdag-het-ziekenhuis-verlaten",
    "type": "article",
    "title": "Belgische koning Albert mag woensdag het ziekenhuis verlaten",
    "subtitle": null,
    "published_at": "2023-07-04T21:14:17+02:00",
    "updated_at": "2023-07-04T21:22:44+02:00",
    "media_id": "fcvxftgaktnj",
    "duration": null,
    "canonical_section": {
      "id": 1778775,
      "slug": "koningshuis",
      "type": "default",
      "name": "Koningshuis",
      "style": "nuuit",
      "media_id": null,
      "partner": null
    },
    "url": "/koningshuis/6270866/belgische-koning-albert-mag-woensdag-het-ziekenhuis-verlaten.html",
    "open_new_window": false,
    "partner": null
  },
  {
    "id": 6270864,
    "slug": "voetbalcoach-vera-pauw-in-2018-bedreigd-door-staflid-schiet-kogel-door-je-hoofd",
    "type": "article",
    "title": "Voetbalcoach Vera Pauw in 2018 bedreigd door staflid: 'Schiet kogel door je hoofd'",
    "subtitle": null,
    "published_at": "2023-07-04T21:01:27+02:00",
    "updated_at": "2023-07-04T22:36:08+02:00",
    "media_id": "c48x2ghazwdt",
    "duration": null,
    "canonical_section": {
      "id": 1772338,
      "slug": "voetbal",
      "type": "default",
      "name": "Voetbal",
      "style": "nusport",
      "media_id": null,
      "partner": null
    },
    "url": "/voetbal/6270864/voetbalcoach-vera-pauw-in-2018-bedreigd-door-staflid-schiet-kogel-door-je-hoofd.html",
    "open_new_window": false,
    "partner": null
  },
  {
    "id": 6270860,
    "slug": "sigaretten-kunnen-tot-wel-vijftien-keer-schadelijker-zijn-dan-eerder-bekend-was",
    "type": "article",
    "title": "Sigaretten kunnen tot wel vijftien keer schadelijker zijn dan eerder bekend was",
    "subtitle": null,
    "published_at": "2023-07-04T20:09:54+02:00",
    "updated_at": "2023-07-04T21:10:49+02:00",
    "media_id": "h37x3snazdo8",
    "duration": null,
    "canonical_section": {
      "id": 1771435,
      "slug": "binnenland",
      "type": "default",
      "name": "Binnenland",
      "style": "nu",
      "media_id": null,
      "partner": null
    },
    "url": "/binnenland/6270860/sigaretten-kunnen-tot-wel-vijftien-keer-schadelijker-zijn-dan-eerder-bekend-was.html",
    "open_new_window": false,
    "partner": null
  },
  {
    "id": 6270856,
    "slug": "ongewenst-delen-van-naaktbeelden-wordt-seksueel-misdrijf",
    "type": "article",
    "title": "Ongewenst delen van naaktbeelden wordt 'seksueel misdrijf'",
    "subtitle": null,
    "published_at": "2023-07-04T19:57:33+02:00",
    "updated_at": "2023-07-04T19:57:34+02:00",
    "media_id": "lflxt7makajl",
    "duration": null,
    "canonical_section": {
      "id": 1771435,
      "slug": "binnenland",
      "type": "default",
      "name": "Binnenland",
      "style": "nu",
      "media_id": null,
      "partner": null
    },
    "url": "/binnenland/6270856/ongewenst-delen-van-naaktbeelden-wordt-seksueel-misdrijf.html",
    "open_new_window": false,
    "partner": null
  },
  {
    "id": 6270851,
    "slug": "vrouw-na-36-uur-uit-grot-van-150-meter-diep-gered-in-italie",
    "type": "article",
    "title": "Vrouw na 36 uur uit grot van 150 meter diep gered in Italië",
    "subtitle": null,
    "published_at": "2023-07-04T19:56:50+02:00",
    "updated_at": "2023-07-04T19:56:52+02:00",
    "media_id": "gbhxlrzamokm",
    "duration": null,
    "canonical_section": {
      "id": 1771436,
      "slug": "buitenland",
      "type": "default",
      "name": "Buitenland",
      "style": "nu",
      "media_id": null,
      "partner": null
    },
    "url": "/buitenland/6270851/vrouw-na-36-uur-uit-grot-van-150-meter-diep-gered-in-italie.html",
    "open_new_window": false,
    "partner": null
  },
  {
    "id": 6270857,
    "slug": "ns-zet-zich-schrap-voor-slecht-weer-schiphol-sluit-s-ochtends-twee-uur-alle-landingsbanen",
    "type": "article",
    "title": "NS zet zich schrap voor slecht weer, Schiphol sluit 's ochtends twee uur alle landingsbanen",
    "subtitle": null,
    "published_at": "2023-07-04T19:37:36+02:00",
    "updated_at": "2023-07-05T01:07:21+02:00",
    "media_id": "eb2x4v9a96pt",
    "duration": null,
    "canonical_section": {
      "id": 1771435,
      "slug": "binnenland",
      "type": "default",
      "name": "Binnenland",
      "style": "nu",
      "media_id": null,
      "partner": null
    },
    "url": "/binnenland/6270857/ns-zet-zich-schrap-voor-slecht-weer-schiphol-sluit-s-ochtends-twee-uur-alle-landingsbanen.html",
    "open_new_window": false,
    "partner": null
  },
  {
    "id": 6270814,
    "slug": "stelling-mobiele-telefoons-horen-niet-thuis-in-het-klaslokaal",
    "type": "article",
    "title": "Stelling: Mobiele telefoons horen niet thuis in het klaslokaal",
    "subtitle": null,
    "published_at": "2023-07-04T19:35:31+02:00",
    "updated_at": "2023-07-04T19:35:32+02:00",
    "media_id": "n0bx5t7al8qm",
    "duration": null,
    "canonical_section": {
      "id": 1779134,
      "slug": "stelling",
      "type": "default",
      "name": "Stelling",
      "style": "nu",
      "media_id": null,
      "partner": null
    },
    "url": "/stelling/6270814/stelling-mobiele-telefoons-horen-niet-thuis-in-het-klaslokaal.html",
    "open_new_window": false,
    "partner": null
  },
  {
    "id": 6270854,
    "slug": "jakobsen-heeft-serieuze-schaafwonden-na-val-philipsen-raakte-fabios-wiel",
    "type": "article",
    "title": "Jakobsen heeft serieuze schaafwonden na val: 'Philipsen raakte Fabio's wiel'",
    "subtitle": null,
    "published_at": "2023-07-04T19:14:31+02:00",
    "updated_at": "2023-07-04T23:25:03+02:00",
    "media_id": "ehzxs76a78it",
    "duration": null,
    "canonical_section": {
      "id": 1772173,
      "slug": "tour-de-france",
      "type": "default",
      "name": "Tour de France",
      "style": "nusport",
      "media_id": null,
      "partner": null
    },
    "url": "/tour-de-france/6270854/jakobsen-heeft-serieuze-schaafwonden-na-val-philipsen-raakte-fabios-wiel.html",
    "open_new_window": false,
    "partner": null
  },
  {
    "id": 6270852,
    "slug": "slavernijmonument-in-vlissingen-moet-van-gemeente-weg",
    "type": "article",
    "title": "Slavernijmonument in Vlissingen moet van gemeente weg",
    "subtitle": null,
    "published_at": "2023-07-04T19:08:40+02:00",
    "updated_at": "2023-07-04T19:08:41+02:00",
    "media_id": "yy1xjt6al93x",
    "duration": null,
    "canonical_section": {
      "id": 1771435,
      "slug": "binnenland",
      "type": "default",
      "name": "Binnenland",
      "style": "nu",
      "media_id": null,
      "partner": null
    },
    "url": "/binnenland/6270852/slavernijmonument-in-vlissingen-moet-van-gemeente-weg.html",
    "open_new_window": false,
    "partner": null
  },
  {
    "id": 6270850,
    "slug": "britse-politie-heeft-nieuw-bewijs-over-partygate-schandaal",
    "type": "article",
    "title": "Britse politie heeft nieuw bewijs over 'partygate'-schandaal",
    "subtitle": null,
    "published_at": "2023-07-04T19:04:44+02:00",
    "updated_at": "2023-07-04T22:05:44+02:00",
    "media_id": "g5wxkh5a1yv1",
    "duration": null,
    "canonical_section": {
      "id": 1779258,
      "slug": "binnenland-en-buitenland",
      "type": "default",
      "name": "Binnen- en buitenland",
      "style": "nu",
      "media_id": null,
      "partner": null
    },
    "url": "/binnenland-en-buitenland/6270850/britse-politie-heeft-nieuw-bewijs-over-partygate-schandaal.html",
    "open_new_window": false,
    "partner": null
  },
  {
    "id": 6270849,
    "slug": "duo-philipsen-van-der-poel-slaat-weer-toe-mathieu-als-lead-out-is-een-voorrecht",
    "type": "article",
    "title": "Duo Philipsen-Van der Poel slaat weer toe: 'Mathieu als lead-out is een voorrecht'",
    "subtitle": null,
    "published_at": "2023-07-04T18:58:04+02:00",
    "updated_at": "2023-07-04T21:21:43+02:00",
    "media_id": "iujxejjavzev",
    "duration": null,
    "canonical_section": {
      "id": 1772173,
      "slug": "tour-de-france",
      "type": "default",
      "name": "Tour de France",
      "style": "nusport",
      "media_id": null,
      "partner": null
    },
    "url": "/tour-de-france/6270849/duo-philipsen-van-der-poel-slaat-weer-toe-mathieu-als-lead-out-is-een-voorrecht.html",
    "open_new_window": false,
    "partner": null
  },
  {
    "id": 6270846,
    "slug": "regen-teistert-wimbledon-partijen-van-nederlanders-verplaatst-naar-woensdag",
    "type": "article",
    "title": "Regen teistert Wimbledon: partijen van Nederlanders verplaatst naar woensdag",
    "subtitle": null,
    "published_at": "2023-07-04T18:32:47+02:00",
    "updated_at": "2023-07-04T22:28:50+02:00",
    "media_id": "tacx6e2a343h",
    "duration": null,
    "canonical_section": {
      "id": 1772432,
      "slug": "tennis",
      "type": "default",
      "name": "Tennis",
      "style": "nusport",
      "media_id": "m1oxohpan0gq",
      "partner": null
    },
    "url": "/tennis/6270846/regen-teistert-wimbledon-partijen-van-nederlanders-verplaatst-naar-woensdag.html",
    "open_new_window": false,
    "partner": null
  }
]
