[
  {
    "id": 6224726,
    "slug": "zelensky-beschuldigt-russische-troepen-van-grootschalige-martelingen",
    "type": "article",
    "title": "Zelensky beschuldigt Russische troepen van grootschalige martelingen",
    "subtitle": null,
    "published_at": "2022-09-18T03:09:53+02:00",
    "updated_at": "2022-09-18T03:09:54+02:00",
    "media_id": "g50xab3adwfm",
    "duration": null,
    "canonical_section": {
      "id": 1778980,
      "slug": "spanningen-oekraine",
      "type": "default",
      "name": "Oorlog in Oekraïne",
      "style": "nu",
      "media_id": null,
      "partner": null
    },
    "url": "/spanningen-oekraine/6224726/zelensky-beschuldigt-russische-troepen-van-grootschalige-martelingen.html",
    "open_new_window": false,
    "partner": null
  },
  {
    "id": 6224725,
    "slug": "cambuur-coach-de-jong-begrijpt-niets-van-penalty-was-nijhuis-de-var",
    "type": "article",
    "title": "Cambuur-coach De Jong begrijpt niets van penalty: 'Was Nijhuis de VAR?'",
    "subtitle": null,
    "published_at": "2022-09-17T23:12:43+02:00",
    "updated_at": "2022-09-17T23:31:17+02:00",
    "media_id": "yqgx0iaa9rek",
    "duration": null,
    "canonical_section": {
      "id": 1772338,
      "slug": "voetbal",
      "type": "default",
      "name": "Voetbal",
      "style": "nusport",
      "media_id": null,
      "partner": null
    },
    "url": "/voetbal/6224725/cambuur-coach-de-jong-begrijpt-niets-van-penalty-was-nijhuis-de-var.html",
    "open_new_window": false,
    "partner": null
  },
  {
    "id": 6224724,
    "slug": "van-gerwen-via-moeizame-winst-op-heta-naar-kwartfinales-world-series-of-darts",
    "type": "article",
    "title": "Van Gerwen via moeizame winst op Heta naar kwartfinales World Series of Darts",
    "subtitle": null,
    "published_at": "2022-09-17T22:55:53+02:00",
    "updated_at": "2022-09-17T23:21:20+02:00",
    "media_id": "o2px7vjat1rm",
    "duration": null,
    "canonical_section": {
      "id": 1777376,
      "slug": "darts",
      "type": "default",
      "name": "Darts",
      "style": "nusport",
      "media_id": null,
      "partner": null
    },
    "url": "/darts/6224724/van-gerwen-via-moeizame-winst-op-heta-naar-kwartfinales-world-series-of-darts.html",
    "open_new_window": false,
    "partner": null
  },
  {
    "id": 6224722,
    "slug": "steward-zwaargewond-na-supportersgeweld-bij-derby-den-bosch-tegen-top-oss",
    "type": "article",
    "title": "Steward zwaargewond na supportersgeweld bij derby Den Bosch tegen TOP Oss",
    "subtitle": null,
    "published_at": "2022-09-17T22:14:37+02:00",
    "updated_at": "2022-09-17T23:25:20+02:00",
    "media_id": "1zmxcimahy78",
    "duration": null,
    "canonical_section": {
      "id": 100,
      "slug": "algemeen",
      "type": "default",
      "name": "Algemeen",
      "style": "nu",
      "media_id": null,
      "partner": null
    },
    "url": "/algemeen/6224722/steward-zwaargewond-na-supportersgeweld-bij-derby-den-bosch-tegen-top-oss.html",
    "open_new_window": false,
    "partner": null
  },
  {
    "id": 6224721,
    "slug": "rkc-krijgt-negental-cambuur-in-slotfase-op-knieen-ook-rood-trainer-henk-de-jong",
    "type": "article",
    "title": "RKC krijgt negental Cambuur in slotfase op knieën, ook rood trainer Henk de Jong",
    "subtitle": null,
    "published_at": "2022-09-17T22:04:32+02:00",
    "updated_at": "2022-09-17T23:20:12+02:00",
    "media_id": "xc2xw06aj8uv",
    "duration": null,
    "canonical_section": {
      "id": 1772338,
      "slug": "voetbal",
      "type": "default",
      "name": "Voetbal",
      "style": "nusport",
      "media_id": null,
      "partner": null
    },
    "url": "/voetbal/6224721/rkc-krijgt-negental-cambuur-in-slotfase-op-knieen-ook-rood-trainer-henk-de-jong.html",
    "open_new_window": false,
    "partner": null
  },
  {
    "id": 6224246,
    "slug": "intuitief-etende-kinderen-lusten-die-alleen-maar-chips-en-koek",
    "type": "article",
    "title": "Intuïtief etende kinderen: lusten die alleen maar chips en koek?",
    "subtitle": null,
    "published_at": "2022-09-17T21:41:42+02:00",
    "updated_at": "2022-09-17T21:41:43+02:00",
    "media_id": "ht1x0q8a1vpy",
    "duration": null,
    "canonical_section": {
      "id": 1778688,
      "slug": "kind-gezin",
      "type": "default",
      "name": "Kind & Gezin",
      "style": "nunjij",
      "media_id": null,
      "partner": null
    },
    "url": "/kind-gezin/6224246/intuitief-etende-kinderen-lusten-die-alleen-maar-chips-en-koek.html",
    "open_new_window": false,
    "partner": null
  },
  {
    "id": 6224243,
    "slug": "moedertaboe-ik-neem-het-mijn-kind-kwalijk-dat-hij-mn-leven-heeft-veranderd",
    "type": "article",
    "title": "Moedertaboe: 'Ik neem het mijn kind kwalijk dat hij m'n leven heeft veranderd'",
    "subtitle": null,
    "published_at": "2022-09-17T21:41:04+02:00",
    "updated_at": "2022-09-17T21:41:05+02:00",
    "media_id": "bwxxgl8anni2",
    "duration": null,
    "canonical_section": {
      "id": 1778688,
      "slug": "kind-gezin",
      "type": "default",
      "name": "Kind & Gezin",
      "style": "nunjij",
      "media_id": null,
      "partner": null
    },
    "url": "/kind-gezin/6224243/moedertaboe-ik-neem-het-mijn-kind-kwalijk-dat-hij-mn-leven-heeft-veranderd.html",
    "open_new_window": false,
    "partner": null
  },
  {
    "id": 6224238,
    "slug": "mijn-gezin-miranda-49-adopteerde-in-haar-eentje-mica-5-uit-haiti",
    "type": "article",
    "title": "Mijn Gezin: Miranda (49) adopteerde in haar eentje Mica (5) uit Haïti",
    "subtitle": null,
    "published_at": "2022-09-17T21:40:20+02:00",
    "updated_at": "2022-09-17T21:40:21+02:00",
    "media_id": "hjsx8y3ah2zi",
    "duration": null,
    "canonical_section": {
      "id": 1778688,
      "slug": "kind-gezin",
      "type": "default",
      "name": "Kind & Gezin",
      "style": "nunjij",
      "media_id": null,
      "partner": null
    },
    "url": "/kind-gezin/6224238/mijn-gezin-miranda-49-adopteerde-in-haar-eentje-mica-5-uit-haiti.html",
    "open_new_window": false,
    "partner": null
  },
  {
    "id": 6224720,
    "slug": "zeshonderd-mensen-in-klederdracht-op-museumplein-voor-boekpresentatie",
    "type": "video",
    "title": "Zeshonderd mensen in klederdracht op Museumplein voor boekpresentatie",
    "subtitle": "Video",
    "published_at": "2022-09-17T21:31:55+02:00",
    "updated_at": "2022-09-17T21:31:55+02:00",
    "media_id": "jyox5veanm83",
    "duration": "0:39",
    "canonical_section": {
      "id": 1771435,
      "slug": "binnenland",
      "type": "default",
      "name": "Binnenland",
      "style": "nu",
      "media_id": null,
      "partner": null
    },
    "url": "/binnenland/6224720/zeshonderd-mensen-in-klederdracht-op-museumplein-voor-boekpresentatie.html",
    "open_new_window": false,
    "partner": null
  },
  {
    "id": 6224718,
    "slug": "weghorst-scoort-bij-gelijkspel-besiktas-in-laatste-duel-voor-interlands-oranje",
    "type": "article",
    "title": "Weghorst scoort bij gelijkspel Besiktas in laatste duel voor interlands Oranje",
    "subtitle": null,
    "published_at": "2022-09-17T21:13:12+02:00",
    "updated_at": "2022-09-17T22:32:18+02:00",
    "media_id": "t3vx2esam65y",
    "duration": null,
    "canonical_section": {
      "id": 1772338,
      "slug": "voetbal",
      "type": "default",
      "name": "Voetbal",
      "style": "nusport",
      "media_id": null,
      "partner": null
    },
    "url": "/voetbal/6224718/weghorst-scoort-bij-gelijkspel-besiktas-in-laatste-duel-voor-interlands-oranje.html",
    "open_new_window": false,
    "partner": null
  },
  {
    "id": 6224717,
    "slug": "opnieuw-miljoenen-van-kabinet-naar-tanker-jemen-schip-is-tikkende-tijdbom",
    "type": "article",
    "title": "Opnieuw miljoenen van kabinet naar tanker Jemen, schip is 'tikkende tijdbom'",
    "subtitle": null,
    "published_at": "2022-09-17T20:50:25+02:00",
    "updated_at": "2022-09-17T21:28:05+02:00",
    "media_id": "mbuxxnaa2ej0",
    "duration": null,
    "canonical_section": {
      "id": 1771436,
      "slug": "buitenland",
      "type": "default",
      "name": "Buitenland",
      "style": "nu",
      "media_id": null,
      "partner": null
    },
    "url": "/buitenland/6224717/opnieuw-miljoenen-van-kabinet-naar-tanker-jemen-schip-is-tikkende-tijdbom.html",
    "open_new_window": false,
    "partner": null
  },
  {
    "id": 6224716,
    "slug": "vitesse-komt-niet-tot-winst-in-airborne-wedstrijd-tegen-fc-volendam",
    "type": "article",
    "title": "Vitesse komt niet tot winst in Airborne-wedstrijd tegen FC Volendam",
    "subtitle": null,
    "published_at": "2022-09-17T20:45:37+02:00",
    "updated_at": "2022-09-17T23:27:46+02:00",
    "media_id": "4l1xu0qaxqjo",
    "duration": null,
    "canonical_section": {
      "id": 1772338,
      "slug": "voetbal",
      "type": "default",
      "name": "Voetbal",
      "style": "nusport",
      "media_id": null,
      "partner": null
    },
    "url": "/voetbal/6224716/vitesse-komt-niet-tot-winst-in-airborne-wedstrijd-tegen-fc-volendam.html",
    "open_new_window": false,
    "partner": null
  },
  {
    "id": 6224715,
    "slug": "kleinkinderen-waken-bij-de-kist-van-elizabeth",
    "type": "video",
    "title": "Kleinkinderen waken bij de kist van Elizabeth",
    "subtitle": "Video",
    "published_at": "2022-09-17T20:42:59+02:00",
    "updated_at": "2022-09-17T20:56:56+02:00",
    "media_id": "14zxz77akj9b",
    "duration": "1:05",
    "canonical_section": {
      "id": 1771436,
      "slug": "buitenland",
      "type": "default",
      "name": "Buitenland",
      "style": "nu",
      "media_id": null,
      "partner": null
    },
    "url": "/buitenland/6224715/kleinkinderen-waken-bij-de-kist-van-elizabeth.html",
    "open_new_window": false,
    "partner": null
  },
  {
    "id": 6224698,
    "slug": "oorlogsveteranen-op-tribune-in-gelredome-voor-airborne-wedstrijd",
    "type": "article",
    "title": "Oorlogsveteranen op tribune in GelreDome voor Airborne-wedstrijd",
    "subtitle": "In beeld",
    "published_at": "2022-09-17T20:01:23+02:00",
    "updated_at": "2022-09-17T21:42:48+02:00",
    "media_id": "kqsx9qba6iey",
    "duration": null,
    "canonical_section": {
      "id": 1772338,
      "slug": "voetbal",
      "type": "default",
      "name": "Voetbal",
      "style": "nusport",
      "media_id": null,
      "partner": null
    },
    "url": "/voetbal/6224698/oorlogsveteranen-op-tribune-in-gelredome-voor-airborne-wedstrijd.html",
    "open_new_window": false,
    "partner": null
  },
  {
    "id": 6224703,
    "slug": "nederland-sluit-davis-cup-week-in-stijl-af-tegen-vs-en-pakt-groepswinst",
    "type": "article",
    "title": "Nederland sluit Davis Cup-week in stijl af tegen VS en pakt groepswinst",
    "subtitle": null,
    "published_at": "2022-09-17T19:44:55+02:00",
    "updated_at": "2022-09-17T20:20:32+02:00",
    "media_id": "w8ux5ofabvbx",
    "duration": null,
    "canonical_section": {
      "id": 1772432,
      "slug": "tennis",
      "type": "default",
      "name": "Tennis",
      "style": "nusport",
      "media_id": "m1oxohpan0gq",
      "partner": null
    },
    "url": "/tennis/6224703/nederland-sluit-davis-cup-week-in-stijl-af-tegen-vs-en-pakt-groepswinst.html",
    "open_new_window": false,
    "partner": null
  },
  {
    "id": 6224702,
    "slug": "zware-regenval-in-kosovo-zorgt-voor-overstromingen",
    "type": "video",
    "title": "Zware regenval in Kosovo zorgt voor overstromingen",
    "subtitle": "Video",
    "published_at": "2022-09-17T19:41:30+02:00",
    "updated_at": "2022-09-17T20:22:27+02:00",
    "media_id": "m9kxlmuaw2du",
    "duration": "0:35",
    "canonical_section": {
      "id": 1771436,
      "slug": "buitenland",
      "type": "default",
      "name": "Buitenland",
      "style": "nu",
      "media_id": null,
      "partner": null
    },
    "url": "/buitenland/6224702/zware-regenval-in-kosovo-zorgt-voor-overstromingen.html",
    "open_new_window": false,
    "partner": null
  },
  {
    "id": 6224699,
    "slug": "as-roma-verdediger-karsdorp-lang-aan-de-kant-na-afscheuren-meniscus",
    "type": "article",
    "title": "AS Roma-verdediger Karsdorp lang aan de kant na afscheuren meniscus",
    "subtitle": null,
    "published_at": "2022-09-17T19:39:56+02:00",
    "updated_at": "2022-09-17T20:08:24+02:00",
    "media_id": "x97xo9uak5ag",
    "duration": null,
    "canonical_section": {
      "id": 1772338,
      "slug": "voetbal",
      "type": "default",
      "name": "Voetbal",
      "style": "nusport",
      "media_id": null,
      "partner": null
    },
    "url": "/voetbal/6224699/as-roma-verdediger-karsdorp-lang-aan-de-kant-na-afscheuren-meniscus.html",
    "open_new_window": false,
    "partner": null
  },
  {
    "id": 6224694,
    "slug": "fc-den-bosch-maakt-einde-aan-dramatische-reeks-en-verlaat-laatste-plek-kkd",
    "type": "article",
    "title": "FC Den Bosch maakt einde aan dramatische reeks en verlaat laatste plek KKD",
    "subtitle": null,
    "published_at": "2022-09-17T19:07:53+02:00",
    "updated_at": "2022-09-17T19:12:53+02:00",
    "media_id": "9bkxddca2cdz",
    "duration": null,
    "canonical_section": {
      "id": 1772338,
      "slug": "voetbal",
      "type": "default",
      "name": "Voetbal",
      "style": "nusport",
      "media_id": null,
      "partner": null
    },
    "url": "/voetbal/6224694/fc-den-bosch-maakt-einde-aan-dramatische-reeks-en-verlaat-laatste-plek-kkd.html",
    "open_new_window": false,
    "partner": null
  },
  {
    "id": 6224693,
    "slug": "van-banden-tot-boeken-vrijwilligers-vissen-40000-kilo-afval-uit-de-maas",
    "type": "article",
    "title": "Van banden tot boeken: vrijwilligers vissen 40.000 kilo afval uit de Maas",
    "subtitle": null,
    "published_at": "2022-09-17T18:44:19+02:00",
    "updated_at": "2022-09-17T18:57:45+02:00",
    "media_id": "5j4xifdap2zz",
    "duration": null,
    "canonical_section": {
      "id": 1771435,
      "slug": "binnenland",
      "type": "default",
      "name": "Binnenland",
      "style": "nu",
      "media_id": null,
      "partner": null
    },
    "url": "/binnenland/6224693/van-banden-tot-boeken-vrijwilligers-vissen-40000-kilo-afval-uit-de-maas.html",
    "open_new_window": false,
    "partner": null
  },
  {
    "id": 6224691,
    "slug": "kipchoge-gaat-voor-wereldrecord-in-berlijn-maar-denkt-niet-aan-tijd-onder-2-uur",
    "type": "article",
    "title": "Kipchoge gaat voor wereldrecord in Berlijn, maar denkt niet aan tijd onder 2 uur",
    "subtitle": null,
    "published_at": "2022-09-17T18:33:49+02:00",
    "updated_at": "2022-09-17T19:15:31+02:00",
    "media_id": "yk4xi4zaywbo",
    "duration": null,
    "canonical_section": {
      "id": 1772456,
      "slug": "sport-overig",
      "type": "default",
      "name": "Sport Overig",
      "style": "nusport",
      "media_id": null,
      "partner": null
    },
    "url": "/sport-overig/6224691/kipchoge-gaat-voor-wereldrecord-in-berlijn-maar-denkt-niet-aan-tijd-onder-2-uur.html",
    "open_new_window": false,
    "partner": null
  },
  {
    "id": 6224692,
    "slug": "honkballers-hcaw-pakken-ten-koste-van-neptunus-eerste-landstitel-in-24-jaar",
    "type": "article",
    "title": "Honkballers HCAW pakken ten koste van Neptunus eerste landstitel in 24 jaar",
    "subtitle": null,
    "published_at": "2022-09-17T18:28:59+02:00",
    "updated_at": "2022-09-17T19:14:16+02:00",
    "media_id": "o3sx4cga40ok",
    "duration": null,
    "canonical_section": {
      "id": 1772456,
      "slug": "sport-overig",
      "type": "default",
      "name": "Sport Overig",
      "style": "nusport",
      "media_id": null,
      "partner": null
    },
    "url": "/sport-overig/6224692/honkballers-hcaw-pakken-ten-koste-van-neptunus-eerste-landstitel-in-24-jaar.html",
    "open_new_window": false,
    "partner": null
  },
  {
    "id": 6224690,
    "slug": "nieuwe-trainer-velazquez-leidt-fortuna-naar-eerste-zege-ook-sparta-wint",
    "type": "article",
    "title": "Nieuwe trainer Velázquez leidt Fortuna naar eerste zege, ook Sparta wint",
    "subtitle": null,
    "published_at": "2022-09-17T18:27:29+02:00",
    "updated_at": "2022-09-17T23:38:02+02:00",
    "media_id": "fu2xsgja52iw",
    "duration": null,
    "canonical_section": {
      "id": 1772338,
      "slug": "voetbal",
      "type": "default",
      "name": "Voetbal",
      "style": "nusport",
      "media_id": null,
      "partner": null
    },
    "url": "/voetbal/6224690/nieuwe-trainer-velazquez-leidt-fortuna-naar-eerste-zege-ook-sparta-wint.html",
    "open_new_window": false,
    "partner": null
  },
  {
    "id": 6224680,
    "slug": "barcelona-wint-met-de-jong-en-scorende-memphis-in-de-basis-simpel-van-elche",
    "type": "article",
    "title": "Barcelona wint met De Jong en scorende Memphis in de basis simpel van Elche",
    "subtitle": null,
    "published_at": "2022-09-17T18:12:00+02:00",
    "updated_at": "2022-09-17T19:19:05+02:00",
    "media_id": "82bx8headrcy",
    "duration": null,
    "canonical_section": {
      "id": 1772338,
      "slug": "voetbal",
      "type": "default",
      "name": "Voetbal",
      "style": "nusport",
      "media_id": null,
      "partner": null
    },
    "url": "/voetbal/6224680/barcelona-wint-met-de-jong-en-scorende-memphis-in-de-basis-simpel-van-elche.html",
    "open_new_window": false,
    "partner": null
  },
  {
    "id": 6224684,
    "slug": "oktoberfest-terug-in-munchen-na-twee-jaar-corona",
    "type": "video",
    "title": "Oktoberfest terug in München na twee jaar corona",
    "subtitle": "Video",
    "published_at": "2022-09-17T17:46:09+02:00",
    "updated_at": "2022-09-17T17:46:56+02:00",
    "media_id": "ik4xhnpanvjg",
    "duration": "0:30",
    "canonical_section": {
      "id": 1771436,
      "slug": "buitenland",
      "type": "default",
      "name": "Buitenland",
      "style": "nu",
      "media_id": null,
      "partner": null
    },
    "url": "/buitenland/6224684/oktoberfest-terug-in-munchen-na-twee-jaar-corona.html",
    "open_new_window": false,
    "partner": null
  },
  {
    "id": 6224683,
    "slug": "bayern-verliest-van-augsburg-en-beleeft-slechtste-bundesliga-reeks-in-21-jaar",
    "type": "article",
    "title": "Bayern verliest van Augsburg en beleeft slechtste Bundesliga-reeks in 21 jaar",
    "subtitle": null,
    "published_at": "2022-09-17T17:29:44+02:00",
    "updated_at": "2022-09-17T23:36:33+02:00",
    "media_id": "y54xrhya5bv8",
    "duration": null,
    "canonical_section": {
      "id": 1772338,
      "slug": "voetbal",
      "type": "default",
      "name": "Voetbal",
      "style": "nusport",
      "media_id": null,
      "partner": null
    },
    "url": "/voetbal/6224683/bayern-verliest-van-augsburg-en-beleeft-slechtste-bundesliga-reeks-in-21-jaar.html",
    "open_new_window": false,
    "partner": null
  },
  {
    "id": 6224681,
    "slug": "voedselbank-verlaagt-drempel-ook-met-ietsje-meer-geld-kun-je-er-nu-terecht",
    "type": "article",
    "title": "Voedselbank verlaagt drempel: ook met iets(je) meer geld kun je er nu terecht",
    "subtitle": null,
    "published_at": "2022-09-17T17:13:56+02:00",
    "updated_at": "2022-09-17T18:38:57+02:00",
    "media_id": "dbvxxp0ariac",
    "duration": null,
    "canonical_section": {
      "id": 1771435,
      "slug": "binnenland",
      "type": "default",
      "name": "Binnenland",
      "style": "nu",
      "media_id": null,
      "partner": null
    },
    "url": "/binnenland/6224681/voedselbank-verlaagt-drempel-ook-met-ietsje-meer-geld-kun-je-er-nu-terecht.html",
    "open_new_window": false,
    "partner": null
  },
  {
    "id": 6224679,
    "slug": "polen-opent-nieuw-kanaal-om-russische-wateren-te-omzeilen",
    "type": "article",
    "title": "Polen opent nieuw kanaal om Russische wateren te omzeilen",
    "subtitle": null,
    "published_at": "2022-09-17T16:47:11+02:00",
    "updated_at": "2022-09-17T17:43:22+02:00",
    "media_id": "9h7xwcdam23x",
    "duration": null,
    "canonical_section": {
      "id": 1771436,
      "slug": "buitenland",
      "type": "default",
      "name": "Buitenland",
      "style": "nu",
      "media_id": null,
      "partner": null
    },
    "url": "/buitenland/6224679/polen-opent-nieuw-kanaal-om-russische-wateren-te-omzeilen.html",
    "open_new_window": false,
    "partner": null
  },
  {
    "id": 6224674,
    "slug": "reacties-na-enerverende-avond-met-zeges-voor-fortuna-rkc-en-sparta",
    "type": "article",
    "title": "Reacties na enerverende avond met zeges voor Fortuna, RKC en Sparta",
    "subtitle": "Liveblog Eredivisie",
    "published_at": "2022-09-17T16:02:41+02:00",
    "updated_at": "2022-09-17T23:19:23+02:00",
    "media_id": "hvhx7blanazh",
    "duration": null,
    "canonical_section": {
      "id": 1772338,
      "slug": "voetbal",
      "type": "default",
      "name": "Voetbal",
      "style": "nusport",
      "media_id": null,
      "partner": null
    },
    "url": "/voetbal/6224674/reacties-na-enerverende-avond-met-zeges-voor-fortuna-rkc-en-sparta.html",
    "open_new_window": false,
    "partner": null
  },
  {
    "id": 6224678,
    "slug": "van-vleuten-ziet-kansen-op-derde-wereldtitel-tijdrijden-parcours-ligt-me-beter",
    "type": "article",
    "title": "Van Vleuten ziet kansen op derde wereldtitel tijdrijden: 'Parcours ligt me beter'",
    "subtitle": null,
    "published_at": "2022-09-17T15:50:54+02:00",
    "updated_at": "2022-09-17T15:57:41+02:00",
    "media_id": "j92xjpuaeoqi",
    "duration": null,
    "canonical_section": {
      "id": 1772339,
      "slug": "wielrennen",
      "type": "default",
      "name": "Wielrennen",
      "style": "nusport",
      "media_id": null,
      "partner": null
    },
    "url": "/wielrennen/6224678/van-vleuten-ziet-kansen-op-derde-wereldtitel-tijdrijden-parcours-ligt-me-beter.html",
    "open_new_window": false,
    "partner": null
  },
  {
    "id": 6223671,
    "slug": "hoe-kom-jij-rond-ik-werk-fulltime-als-monteur-en-doe-er-voor-de-lol-horecawerk-bij",
    "type": "article",
    "title": "Hoe kom jij rond? 'Ik werk fulltime als monteur en doe er voor de lol horecawerk bij'",
    "subtitle": null,
    "published_at": "2022-09-17T15:30:48+02:00",
    "updated_at": "2022-09-17T20:17:21+02:00",
    "media_id": "ci2x04qaztv1",
    "duration": null,
    "canonical_section": {
      "id": 1771719,
      "slug": "geldzaken",
      "type": "default",
      "name": "Geld",
      "style": "nuzakelijk",
      "media_id": null,
      "partner": null
    },
    "url": "/geldzaken/6223671/hoe-kom-jij-rond-ik-werk-fulltime-als-monteur-en-doe-er-voor-de-lol-horecawerk-bij.html",
    "open_new_window": false,
    "partner": null
  }
]
